{
"meta":{"test_sets":[],"test_metrics":[],"learn_metrics":[{"best_value":"Min","name":"RMSE"}],"launch_mode":"Train","parameters":"","iteration_count":1000,"learn_sets":["learn"],"name":"experiment"},
"iterations":[
{"learn":[14.59871775],"iteration":0,"passed_time":0.09665168907,"remaining_time":96.55503738},
{"learn":[14.22518863],"iteration":1,"passed_time":0.09725351923,"remaining_time":48.5295061},
{"learn":[13.8866124],"iteration":2,"passed_time":0.09807338446,"remaining_time":32.59305477},
{"learn":[13.52356875],"iteration":3,"passed_time":0.09882840622,"remaining_time":24.60827315},
{"learn":[13.18870211],"iteration":4,"passed_time":0.0994846753,"remaining_time":19.79745038},
{"learn":[12.9124226],"iteration":5,"passed_time":0.1001204002,"remaining_time":16.58661296},
{"learn":[12.60003351],"iteration":6,"passed_time":0.1007445258,"remaining_time":14.29133059},
{"learn":[12.32990573],"iteration":7,"passed_time":0.1013437977,"remaining_time":12.56663092},
{"learn":[12.0660619],"iteration":8,"passed_time":0.1019428695,"remaining_time":11.22504263},
{"learn":[11.77309809],"iteration":9,"passed_time":0.1024596862,"remaining_time":10.14350894},
{"learn":[11.49227636],"iteration":10,"passed_time":0.1029759059,"remaining_time":9.258470081},
{"learn":[11.26264833],"iteration":11,"passed_time":0.1035259246,"remaining_time":8.523634456},
{"learn":[11.04260393],"iteration":12,"passed_time":0.1040633335,"remaining_time":7.900808478},
{"learn":[10.79916926],"iteration":13,"passed_time":0.1046750541,"remaining_time":7.372114523},
{"learn":[10.5541002],"iteration":14,"passed_time":0.105213628,"remaining_time":6.909028237},
{"learn":[10.31918115],"iteration":15,"passed_time":0.1057559429,"remaining_time":6.503990488},
{"learn":[10.10004441],"iteration":16,"passed_time":0.1063020052,"remaining_time":6.146757121},
{"learn":[9.894556723],"iteration":17,"passed_time":0.1070602753,"remaining_time":5.840732799},
{"learn":[9.690174082],"iteration":18,"passed_time":0.1082484418,"remaining_time":5.589037966},
{"learn":[9.506034866],"iteration":19,"passed_time":0.1089117293,"remaining_time":5.336674736},
{"learn":[9.338524633],"iteration":20,"passed_time":0.109515752,"remaining_time":5.105520057},
{"learn":[9.170203312],"iteration":21,"passed_time":0.1100920241,"remaining_time":4.89409089},
{"learn":[9.010299969],"iteration":22,"passed_time":0.1106625729,"remaining_time":4.70075364},
{"learn":[8.843866678],"iteration":23,"passed_time":0.1112519872,"remaining_time":4.524247478},
{"learn":[8.690548059],"iteration":24,"passed_time":0.1118729719,"remaining_time":4.363045904},
{"learn":[8.555307687],"iteration":25,"passed_time":0.1124480802,"remaining_time":4.212478083},
{"learn":[8.413851302],"iteration":26,"passed_time":0.1130256397,"remaining_time":4.073109163},
{"learn":[8.29256019],"iteration":27,"passed_time":0.1136300761,"remaining_time":3.944586928},
{"learn":[8.162193833],"iteration":28,"passed_time":0.114208726,"remaining_time":3.824023206},
{"learn":[8.040736294],"iteration":29,"passed_time":0.1147608193,"remaining_time":3.710599825},
{"learn":[7.921220278],"iteration":30,"passed_time":0.1152871485,"remaining_time":3.603653125},
{"learn":[7.809589039],"iteration":31,"passed_time":0.1158416583,"remaining_time":3.504210163},
{"learn":[7.699675801],"iteration":32,"passed_time":0.1164649319,"remaining_time":3.412775429},
{"learn":[7.60645267],"iteration":33,"passed_time":0.1170709883,"remaining_time":3.326193373},
{"learn":[7.498880302],"iteration":34,"passed_time":0.1176219044,"remaining_time":3.243003935},
{"learn":[7.401158744],"iteration":35,"passed_time":0.1182584351,"remaining_time":3.166698096},
{"learn":[7.306431077],"iteration":36,"passed_time":0.1188711007,"remaining_time":3.09386135},
{"learn":[7.223863468],"iteration":37,"passed_time":0.1195400881,"remaining_time":3.026251705},
{"learn":[7.143477682],"iteration":38,"passed_time":0.1201121385,"remaining_time":2.959686285},
{"learn":[7.062817131],"iteration":39,"passed_time":0.1206940667,"remaining_time":2.8966576},
{"learn":[6.990793435],"iteration":40,"passed_time":0.1212512564,"remaining_time":2.83609646},
{"learn":[6.931862224],"iteration":41,"passed_time":0.1217601283,"remaining_time":2.777290545},
{"learn":[6.858296558],"iteration":42,"passed_time":0.1222979953,"remaining_time":2.721841429},
{"learn":[6.786268161],"iteration":43,"passed_time":0.1227981967,"remaining_time":2.668069911},
{"learn":[6.717118549],"iteration":44,"passed_time":0.1233680423,"remaining_time":2.61814401},
{"learn":[6.652948106],"iteration":45,"passed_time":0.1239746594,"remaining_time":2.571126631},
{"learn":[6.589686076],"iteration":46,"passed_time":0.1245782096,"remaining_time":2.526021994},
{"learn":[6.531283097],"iteration":47,"passed_time":0.1252011893,"remaining_time":2.48315692},
{"learn":[6.471368031],"iteration":48,"passed_time":0.1258534115,"remaining_time":2.442583558},
{"learn":[6.416481395],"iteration":49,"passed_time":0.1264496344,"remaining_time":2.402543053},
{"learn":[6.369870822],"iteration":50,"passed_time":0.1270085103,"remaining_time":2.363354436},
{"learn":[6.325678067],"iteration":51,"passed_time":0.127582969,"remaining_time":2.325935666},
{"learn":[6.275766122],"iteration":52,"passed_time":0.1281518022,"remaining_time":2.28980673},
{"learn":[6.224773967],"iteration":53,"passed_time":0.1286175863,"remaining_time":2.253189567},
{"learn":[6.182249254],"iteration":54,"passed_time":0.1292061556,"remaining_time":2.219996673},
{"learn":[6.139904173],"iteration":55,"passed_time":0.129797816,"remaining_time":2.188020326},
{"learn":[6.100525536],"iteration":56,"passed_time":0.1303502865,"remaining_time":2.156496846},
{"learn":[6.062568564],"iteration":57,"passed_time":0.1309239037,"remaining_time":2.12638478},
{"learn":[6.030559288],"iteration":58,"passed_time":0.1316128341,"remaining_time":2.099113167},
{"learn":[5.997931376],"iteration":59,"passed_time":0.132157468,"remaining_time":2.070466999},
{"learn":[5.964103835],"iteration":60,"passed_time":0.1327480959,"remaining_time":2.043450198},
{"learn":[5.933729724],"iteration":61,"passed_time":0.1332863655,"remaining_time":2.016493723},
{"learn":[5.901932711],"iteration":62,"passed_time":0.1338661055,"remaining_time":1.990992713},
{"learn":[5.873727795],"iteration":63,"passed_time":0.1344245268,"remaining_time":1.965958704},
{"learn":[5.846485734],"iteration":64,"passed_time":0.135049427,"remaining_time":1.942634066},
{"learn":[5.820630862],"iteration":65,"passed_time":0.1356015877,"remaining_time":1.918967923},
{"learn":[5.793646238],"iteration":66,"passed_time":0.1361017151,"remaining_time":1.895267167},
{"learn":[5.765388646],"iteration":67,"passed_time":0.1366762587,"remaining_time":1.873268722},
{"learn":[5.747073912],"iteration":68,"passed_time":0.1372240931,"remaining_time":1.851530879},
{"learn":[5.722315217],"iteration":69,"passed_time":0.1378901346,"remaining_time":1.831968931},
{"learn":[5.699970599],"iteration":70,"passed_time":0.1384580827,"remaining_time":1.811655758},
{"learn":[5.682732647],"iteration":71,"passed_time":0.139011035,"remaining_time":1.791697785},
{"learn":[5.663525791],"iteration":72,"passed_time":0.1395187625,"remaining_time":1.771697162},
{"learn":[5.642381613],"iteration":73,"passed_time":0.1400106779,"remaining_time":1.75202551},
{"learn":[5.621404779],"iteration":74,"passed_time":0.1405552519,"remaining_time":1.733514774},
{"learn":[5.602460129],"iteration":75,"passed_time":0.1411466671,"remaining_time":1.716046321},
{"learn":[5.587337574],"iteration":76,"passed_time":0.1417143764,"remaining_time":1.69873207},
{"learn":[5.572393026],"iteration":77,"passed_time":0.1423153966,"remaining_time":1.68224097},
{"learn":[5.558425806],"iteration":78,"passed_time":0.1429268976,"remaining_time":1.666274338},
{"learn":[5.541518902],"iteration":79,"passed_time":0.1435141577,"remaining_time":1.650412813},
{"learn":[5.526157283],"iteration":80,"passed_time":0.1441750001,"remaining_time":1.635763272},
{"learn":[5.511746977],"iteration":81,"passed_time":0.144794693,"remaining_time":1.620994246},
{"learn":[5.504975022],"iteration":82,"passed_time":0.1450834765,"remaining_time":1.602910216},
{"learn":[5.493980522],"iteration":83,"passed_time":0.1456632656,"remaining_time":1.58842323},
{"learn":[5.480745463],"iteration":84,"passed_time":0.1462476784,"remaining_time":1.574313243},
{"learn":[5.464052013],"iteration":85,"passed_time":0.1467814899,"remaining_time":1.559980021},
{"learn":[5.449143727],"iteration":86,"passed_time":0.1472907447,"remaining_time":1.54570632},
{"learn":[5.438255432],"iteration":87,"passed_time":0.1478667444,"remaining_time":1.53243717},
{"learn":[5.425927931],"iteration":88,"passed_time":0.1484416489,"remaining_time":1.519442046},
{"learn":[5.412331217],"iteration":89,"passed_time":0.1490142533,"remaining_time":1.506699672},
{"learn":[5.400691499],"iteration":90,"passed_time":0.1495426897,"remaining_time":1.493783571},
{"learn":[5.391618744],"iteration":91,"passed_time":0.1501778219,"remaining_time":1.482189808},
{"learn":[5.380766572],"iteration":92,"passed_time":0.1508458822,"remaining_time":1.471152851},
{"learn":[5.372207183],"iteration":93,"passed_time":0.1515276271,"remaining_time":1.460468406},
{"learn":[5.362918837],"iteration":94,"passed_time":0.1521140169,"remaining_time":1.449086161},
{"learn":[5.348292324],"iteration":95,"passed_time":0.1526563776,"remaining_time":1.437514222},
{"learn":[5.339772295],"iteration":96,"passed_time":0.1532218623,"remaining_time":1.426384966},
{"learn":[5.331515983],"iteration":97,"passed_time":0.1538741675,"remaining_time":1.416270399},
{"learn":[5.323861644],"iteration":98,"passed_time":0.1544717045,"remaining_time":1.405848543},
{"learn":[5.313277281],"iteration":99,"passed_time":0.1549708404,"remaining_time":1.394737564},
{"learn":[5.30685627],"iteration":100,"passed_time":0.1555521919,"remaining_time":1.38456852},
{"learn":[5.29652059],"iteration":101,"passed_time":0.1561264363,"remaining_time":1.3745249},
{"learn":[5.288350766],"iteration":102,"passed_time":0.156843259,"remaining_time":1.365906829},
{"learn":[5.27993346],"iteration":103,"passed_time":0.1574111004,"remaining_time":1.356157172},
{"learn":[5.271789139],"iteration":104,"passed_time":0.1579276195,"remaining_time":1.346144947},
{"learn":[5.262684686],"iteration":105,"passed_time":0.1584772263,"remaining_time":1.336590947},
{"learn":[5.251619772],"iteration":106,"passed_time":0.159035626,"remaining_time":1.327278636},
{"learn":[5.241012171],"iteration":107,"passed_time":0.1595696277,"remaining_time":1.317926925},
{"learn":[5.232684032],"iteration":108,"passed_time":0.160145143,"remaining_time":1.309076353},
{"learn":[5.224267141],"iteration":109,"passed_time":0.1607100135,"remaining_time":1.300290109},
{"learn":[5.216324968],"iteration":110,"passed_time":0.1612721378,"remaining_time":1.291630005},
{"learn":[5.211102527],"iteration":111,"passed_time":0.1617970725,"remaining_time":1.282819646},
{"learn":[5.206364257],"iteration":112,"passed_time":0.1623647069,"remaining_time":1.274491107},
{"learn":[5.196937641],"iteration":113,"passed_time":0.1629755922,"remaining_time":1.266634866},
{"learn":[5.190746047],"iteration":114,"passed_time":0.1635885439,"remaining_time":1.258920533},
{"learn":[5.181885213],"iteration":115,"passed_time":0.1641532841,"remaining_time":1.250961234},
{"learn":[5.178293568],"iteration":116,"passed_time":0.1645726861,"remaining_time":1.242031469},
{"learn":[5.170991438],"iteration":117,"passed_time":0.1651674007,"remaining_time":1.234556334},
{"learn":[5.166257212],"iteration":118,"passed_time":0.1657045846,"remaining_time":1.226770916},
{"learn":[5.161421246],"iteration":119,"passed_time":0.1666671182,"remaining_time":1.222225533},
{"learn":[5.158223542],"iteration":120,"passed_time":0.167251766,"remaining_time":1.214994234},
{"learn":[5.15470988],"iteration":121,"passed_time":0.1677185461,"remaining_time":1.207023635},
{"learn":[5.146388143],"iteration":122,"passed_time":0.1682704846,"remaining_time":1.199782236},
{"learn":[5.139529364],"iteration":123,"passed_time":0.1688593627,"remaining_time":1.192909692},
{"learn":[5.134276023],"iteration":124,"passed_time":0.1695267009,"remaining_time":1.186686906},
{"learn":[5.128536065],"iteration":125,"passed_time":0.1701343745,"remaining_time":1.180138439},
{"learn":[5.123300353],"iteration":126,"passed_time":0.1706006519,"remaining_time":1.172711568},
{"learn":[5.116200518],"iteration":127,"passed_time":0.1711838216,"remaining_time":1.166189785},
{"learn":[5.108728704],"iteration":128,"passed_time":0.1717685327,"remaining_time":1.159770481},
{"learn":[5.104075866],"iteration":129,"passed_time":0.1723129873,"remaining_time":1.153171531},
{"learn":[5.100317606],"iteration":130,"passed_time":0.1728931936,"remaining_time":1.146902177},
{"learn":[5.095814182],"iteration":131,"passed_time":0.1734278639,"remaining_time":1.14041959},
{"learn":[5.092146915],"iteration":132,"passed_time":0.1738969696,"remaining_time":1.133599043},
{"learn":[5.085258329],"iteration":133,"passed_time":0.1744178016,"remaining_time":1.127207584},
{"learn":[5.079219421],"iteration":134,"passed_time":0.174981096,"remaining_time":1.121175171},
{"learn":[5.076476829],"iteration":135,"passed_time":0.1756959268,"remaining_time":1.116185888},
{"learn":[5.072133867],"iteration":136,"passed_time":0.1763248709,"remaining_time":1.110717983},
{"learn":[5.067031564],"iteration":137,"passed_time":0.1768927617,"remaining_time":1.104938845},
{"learn":[5.061358312],"iteration":138,"passed_time":0.1773961804,"remaining_time":1.098835333},
{"learn":[5.056759124],"iteration":139,"passed_time":0.1779380656,"remaining_time":1.093048117},
{"learn":[5.050254],"iteration":140,"passed_time":0.1784671353,"remaining_time":1.087257229},
{"learn":[5.048376474],"iteration":141,"passed_time":0.1788102189,"remaining_time":1.080416675},
{"learn":[5.042603751],"iteration":142,"passed_time":0.1793498289,"remaining_time":1.074844779},
{"learn":[5.037477349],"iteration":143,"passed_time":0.1798744637,"remaining_time":1.069253757},
{"learn":[5.03230489],"iteration":144,"passed_time":0.1804186653,"remaining_time":1.063847992},
{"learn":[5.025976187],"iteration":145,"passed_time":0.1809410771,"remaining_time":1.058381369},
{"learn":[5.01952451],"iteration":146,"passed_time":0.1815248279,"remaining_time":1.053337947},
{"learn":[5.017569424],"iteration":147,"passed_time":0.1821597395,"remaining_time":1.048649311},
{"learn":[5.008962367],"iteration":148,"passed_time":0.1827188494,"remaining_time":1.043582153},
{"learn":[5.003880266],"iteration":149,"passed_time":0.18323603,"remaining_time":1.038337504},
{"learn":[4.996387564],"iteration":150,"passed_time":0.1837529547,"remaining_time":1.03315403},
{"learn":[4.993361683],"iteration":151,"passed_time":0.1843090473,"remaining_time":1.028250474},
{"learn":[4.99005752],"iteration":152,"passed_time":0.1850260932,"remaining_time":1.024294778},
{"learn":[4.986908764],"iteration":153,"passed_time":0.1855864127,"remaining_time":1.019520163},
{"learn":[4.985207175],"iteration":154,"passed_time":0.1861403183,"remaining_time":1.014764961},
{"learn":[4.979003494],"iteration":155,"passed_time":0.186715184,"remaining_time":1.010177021},
{"learn":[4.973142217],"iteration":156,"passed_time":0.187268635,"remaining_time":1.005525218},
{"learn":[4.967056696],"iteration":157,"passed_time":0.1880119567,"remaining_time":1.001937136},
{"learn":[4.961460696],"iteration":158,"passed_time":0.1886888574,"remaining_time":0.9980335161},
{"learn":[4.954240363],"iteration":159,"passed_time":0.1892071084,"remaining_time":0.9933373193},
{"learn":[4.952320707],"iteration":160,"passed_time":0.1895862257,"remaining_time":0.987967971},
{"learn":[4.948337777],"iteration":161,"passed_time":0.1901002293,"remaining_time":0.9833579764},
{"learn":[4.943228639],"iteration":162,"passed_time":0.1907243535,"remaining_time":0.9793637047},
{"learn":[4.938545759],"iteration":163,"passed_time":0.1912677187,"remaining_time":0.9749988588},
{"learn":[4.935330572],"iteration":164,"passed_time":0.1917680526,"remaining_time":0.9704625694},
{"learn":[4.932051543],"iteration":165,"passed_time":0.1923105967,"remaining_time":0.966186974},
{"learn":[4.928964153],"iteration":166,"passed_time":0.1928453094,"remaining_time":0.9619170225},
{"learn":[4.922860227],"iteration":167,"passed_time":0.1934088598,"remaining_time":0.9578343535},
{"learn":[4.917668772],"iteration":168,"passed_time":0.1939999818,"remaining_time":0.9539289048},
{"learn":[4.910365386],"iteration":169,"passed_time":0.1947333243,"remaining_time":0.9507568184},
{"learn":[4.906457206],"iteration":170,"passed_time":0.1953070225,"remaining_time":0.9468393079},
{"learn":[4.901996508],"iteration":171,"passed_time":0.1958783027,"remaining_time":0.9429490388},
{"learn":[4.896816173],"iteration":172,"passed_time":0.1964323333,"remaining_time":0.9390146802},
{"learn":[4.891123132],"iteration":173,"passed_time":0.1970169455,"remaining_time":0.9352643504},
{"learn":[4.887630202],"iteration":174,"passed_time":0.1975169312,"remaining_time":0.9311512469},
{"learn":[4.885259712],"iteration":175,"passed_time":0.1980198234,"remaining_time":0.9270928094},
{"learn":[4.880659728],"iteration":176,"passed_time":0.1985443335,"remaining_time":0.9231750649},
{"learn":[4.877299723],"iteration":177,"passed_time":0.1990705034,"remaining_time":0.9193031113},
{"learn":[4.874038772],"iteration":178,"passed_time":0.1995873321,"remaining_time":0.9154256964},
{"learn":[4.86943698],"iteration":179,"passed_time":0.2001906148,"remaining_time":0.9119794673},
{"learn":[4.861268711],"iteration":180,"passed_time":0.2007847051,"remaining_time":0.9085230577},
{"learn":[4.858673056],"iteration":181,"passed_time":0.2014018364,"remaining_time":0.9052016603},
{"learn":[4.854036207],"iteration":182,"passed_time":0.201896687,"remaining_time":0.9013638976},
{"learn":[4.85130244],"iteration":183,"passed_time":0.2024242904,"remaining_time":0.8977077227},
{"learn":[4.847510084],"iteration":184,"passed_time":0.2029607443,"remaining_time":0.8941243601},
{"learn":[4.845691673],"iteration":185,"passed_time":0.203448761,"remaining_time":0.8903617818},
{"learn":[4.842058646],"iteration":186,"passed_time":0.2039769958,"remaining_time":0.8868090779},
{"learn":[4.838623675],"iteration":187,"passed_time":0.204496975,"remaining_time":0.8832528921},
{"learn":[4.834602161],"iteration":188,"passed_time":0.2050955013,"remaining_time":0.8800658814},
{"learn":[4.830858976],"iteration":189,"passed_time":0.2056935596,"remaining_time":0.8769041224},
{"learn":[4.827590511],"iteration":190,"passed_time":0.2062608905,"remaining_time":0.8736390596},
{"learn":[4.822246226],"iteration":191,"passed_time":0.2068632824,"remaining_time":0.8705496469},
{"learn":[4.816686395],"iteration":192,"passed_time":0.2073800341,"remaining_time":0.8671279146},
{"learn":[4.814797121],"iteration":193,"passed_time":0.2078883937,"remaining_time":0.8637012644},
{"learn":[4.811639392],"iteration":194,"passed_time":0.2084074595,"remaining_time":0.8603487431},
{"learn":[4.804813432],"iteration":195,"passed_time":0.2089606824,"remaining_time":0.8571652481},
{"learn":[4.80251613],"iteration":196,"passed_time":0.2094927936,"remaining_time":0.8539224025},
{"learn":[4.800087884],"iteration":197,"passed_time":0.2100173124,"remaining_time":0.8506761844},
{"learn":[4.794773135],"iteration":198,"passed_time":0.2105100976,"remaining_time":0.847329589},
{"learn":[4.791664833],"iteration":199,"passed_time":0.2110285314,"remaining_time":0.8441141255},
{"learn":[4.785989873],"iteration":200,"passed_time":0.2116141916,"remaining_time":0.8411927318},
{"learn":[4.782387142],"iteration":201,"passed_time":0.2121146956,"remaining_time":0.8379580547},
{"learn":[4.778623704],"iteration":202,"passed_time":0.2127251753,"remaining_time":0.8351820922},
{"learn":[4.775772178],"iteration":203,"passed_time":0.2136153781,"remaining_time":0.8335188285},
{"learn":[4.77023101],"iteration":204,"passed_time":0.2142616903,"remaining_time":0.8309172866},
{"learn":[4.764496689],"iteration":205,"passed_time":0.2148076416,"remaining_time":0.8279479003},
{"learn":[4.763138716],"iteration":206,"passed_time":0.2153429891,"remaining_time":0.8249613059},
{"learn":[4.758053283],"iteration":207,"passed_time":0.2158041551,"remaining_time":0.8217158215},
{"learn":[4.755063788],"iteration":208,"passed_time":0.216312056,"remaining_time":0.8186738577},
{"learn":[4.752465267],"iteration":209,"passed_time":0.2168376332,"remaining_time":0.8157225248},
{"learn":[4.748067377],"iteration":210,"passed_time":0.2173865919,"remaining_time":0.8128816161},
{"learn":[4.744163298],"iteration":211,"passed_time":0.2178806396,"remaining_time":0.8098582263},
{"learn":[4.736670896],"iteration":212,"passed_time":0.2183786504,"remaining_time":0.8068732293},
{"learn":[4.73349255],"iteration":213,"passed_time":0.218895555,"remaining_time":0.8039808701},
{"learn":[4.731864595],"iteration":214,"passed_time":0.2194735118,"remaining_time":0.8013335197},
{"learn":[4.728398311],"iteration":215,"passed_time":0.2200319758,"remaining_time":0.7986345788},
{"learn":[4.723865975],"iteration":216,"passed_time":0.2206022005,"remaining_time":0.7959978018},
{"learn":[4.723483365],"iteration":217,"passed_time":0.2211510822,"remaining_time":0.7933034233},
{"learn":[4.72095416],"iteration":218,"passed_time":0.221633291,"remaining_time":0.790390869},
{"learn":[4.716173382],"iteration":219,"passed_time":0.2221703845,"remaining_time":0.7876949997},
{"learn":[4.710563974],"iteration":220,"passed_time":0.2227176348,"remaining_time":0.7850544682},
{"learn":[4.707160263],"iteration":221,"passed_time":0.2233063853,"remaining_time":0.7825782331},
{"learn":[4.70408351],"iteration":222,"passed_time":0.2238524245,"remaining_time":0.7799701068},
{"learn":[4.702501831],"iteration":223,"passed_time":0.2243998254,"remaining_time":0.7773851095},
{"learn":[4.700269738],"iteration":224,"passed_time":0.2250072673,"remaining_time":0.7750250318},
{"learn":[4.695346302],"iteration":225,"passed_time":0.2256630081,"remaining_time":0.7728458772},
{"learn":[4.689769299],"iteration":226,"passed_time":0.2262597872,"remaining_time":0.7704793634},
{"learn":[4.687919514],"iteration":227,"passed_time":0.2267456667,"remaining_time":0.7677528716},
{"learn":[4.682982074],"iteration":228,"passed_time":0.2272875687,"remaining_time":0.7652345652},
{"learn":[4.679578702],"iteration":229,"passed_time":0.2278143253,"remaining_time":0.7626827412},
{"learn":[4.675751423],"iteration":230,"passed_time":0.2283047,"remaining_time":0.7600273347},
{"learn":[4.672710726],"iteration":231,"passed_time":0.2288437509,"remaining_time":0.7575517271},
{"learn":[4.6690533],"iteration":232,"passed_time":0.2293794257,"remaining_time":0.7550816289},
{"learn":[4.667595702],"iteration":233,"passed_time":0.2299177131,"remaining_time":0.7526366165},
{"learn":[4.664241291],"iteration":234,"passed_time":0.2304320546,"remaining_time":0.7501298799},
{"learn":[4.662246999],"iteration":235,"passed_time":0.2309895911,"remaining_time":0.7477798627},
{"learn":[4.658668443],"iteration":236,"passed_time":0.23159834,"remaining_time":0.7456098457},
{"learn":[4.658017572],"iteration":237,"passed_time":0.2323023063,"remaining_time":0.7437578043},
{"learn":[4.657656705],"iteration":238,"passed_time":0.2328403445,"remaining_time":0.7413870382},
{"learn":[4.653242871],"iteration":239,"passed_time":0.23335688,"remaining_time":0.7389634532},
{"learn":[4.6507302],"iteration":240,"passed_time":0.233929196,"remaining_time":0.7367313684},
{"learn":[4.647671336],"iteration":241,"passed_time":0.234450223,"remaining_time":0.7343523513},
{"learn":[4.645506007],"iteration":242,"passed_time":0.234947704,"remaining_time":0.7319152754},
{"learn":[4.641297906],"iteration":243,"passed_time":0.2354572545,"remaining_time":0.7295314935},
{"learn":[4.63798107],"iteration":244,"passed_time":0.2360116129,"remaining_time":0.7273010928},
{"learn":[4.635062318],"iteration":245,"passed_time":0.2364984058,"remaining_time":0.7248772276},
{"learn":[4.631606017],"iteration":246,"passed_time":0.2370403215,"remaining_time":0.7226370936},
{"learn":[4.630215494],"iteration":247,"passed_time":0.2375837887,"remaining_time":0.7204153593},
{"learn":[4.62729814],"iteration":248,"passed_time":0.2381624011,"remaining_time":0.7183131052},
{"learn":[4.624691756],"iteration":249,"passed_time":0.2387248997,"remaining_time":0.716174699},
{"learn":[4.621840053],"iteration":250,"passed_time":0.2393276853,"remaining_time":0.7141690688},
{"learn":[4.619602091],"iteration":251,"passed_time":0.2398617666,"remaining_time":0.7119706405},
{"learn":[4.613584029],"iteration":252,"passed_time":0.2404620274,"remaining_time":0.7099807687},
{"learn":[4.6119388],"iteration":253,"passed_time":0.2410647687,"remaining_time":0.7080091239},
{"learn":[4.60870702],"iteration":254,"passed_time":0.2417048615,"remaining_time":0.7061573406},
{"learn":[4.604771557],"iteration":255,"passed_time":0.2422964192,"remaining_time":0.7041739684},
{"learn":[4.604231277],"iteration":256,"passed_time":0.2428642807,"remaining_time":0.7021329203},
{"learn":[4.600750354],"iteration":257,"passed_time":0.2434008008,"remaining_time":0.7000131558},
{"learn":[4.596488253],"iteration":258,"passed_time":0.2439937715,"remaining_time":0.6980671225},
{"learn":[4.59470784],"iteration":259,"passed_time":0.2445981849,"remaining_time":0.6961640647},
{"learn":[4.588818005],"iteration":260,"passed_time":0.245208617,"remaining_time":0.6942879999},
{"learn":[4.585054174],"iteration":261,"passed_time":0.2457336927,"remaining_time":0.6921811649},
{"learn":[4.581471435],"iteration":262,"passed_time":0.2462550471,"remaining_time":0.6900759304},
{"learn":[4.577555199],"iteration":263,"passed_time":0.2467942203,"remaining_time":0.6880323718},
{"learn":[4.57457145],"iteration":264,"passed_time":0.2473197964,"remaining_time":0.6859624543},
{"learn":[4.573029224],"iteration":265,"passed_time":0.2478402248,"remaining_time":0.6838899435},
{"learn":[4.571326203],"iteration":266,"passed_time":0.2484033778,"remaining_time":0.6819463518},
{"learn":[4.571019224],"iteration":267,"passed_time":0.2489287031,"remaining_time":0.6799097414},
{"learn":[4.565766631],"iteration":268,"passed_time":0.2495378822,"remaining_time":0.6781122374},
{"learn":[4.563383471],"iteration":269,"passed_time":0.2501137688,"remaining_time":0.6762335231},
{"learn":[4.558165805],"iteration":270,"passed_time":0.2507961451,"remaining_time":0.6746508848},
{"learn":[4.55629209],"iteration":271,"passed_time":0.2514243567,"remaining_time":0.6729298958},
{"learn":[4.549383848],"iteration":272,"passed_time":0.2519792776,"remaining_time":0.6710217392},
{"learn":[4.546227503],"iteration":273,"passed_time":0.252461421,"remaining_time":0.6689306263},
{"learn":[4.540620977],"iteration":274,"passed_time":0.2530628467,"remaining_time":0.6671656867},
{"learn":[4.532898237],"iteration":275,"passed_time":0.2535796382,"remaining_time":0.6651871668},
{"learn":[4.529757367],"iteration":276,"passed_time":0.2540789586,"remaining_time":0.6631735996},
{"learn":[4.52579294],"iteration":277,"passed_time":0.2545878592,"remaining_time":0.6611958069},
{"learn":[4.521572155],"iteration":278,"passed_time":0.2551547685,"remaining_time":0.6593784519},
{"learn":[4.518818099],"iteration":279,"passed_time":0.2556564188,"remaining_time":0.6574022197},
{"learn":[4.514012334],"iteration":280,"passed_time":0.2561843239,"remaining_time":0.6555036616},
{"learn":[4.508331416],"iteration":281,"passed_time":0.2570510452,"remaining_time":0.6544774838},
{"learn":[4.506038537],"iteration":282,"passed_time":0.2577203016,"remaining_time":0.6529521423},
{"learn":[4.505805643],"iteration":283,"passed_time":0.2583373965,"remaining_time":0.6513013236},
{"learn":[4.501550352],"iteration":284,"passed_time":0.2589538035,"remaining_time":0.6496560333},
{"learn":[4.494692643],"iteration":285,"passed_time":0.2595694697,"remaining_time":0.6480160886},
{"learn":[4.489330245],"iteration":286,"passed_time":0.2600803823,"remaining_time":0.6461230403},
{"learn":[4.484826955],"iteration":287,"passed_time":0.2606568866,"remaining_time":0.6444017474},
{"learn":[4.478285428],"iteration":288,"passed_time":0.261215249,"remaining_time":0.6426437442},
{"learn":[4.475311671],"iteration":289,"passed_time":0.2617784441,"remaining_time":0.640905846},
{"learn":[4.471581298],"iteration":290,"passed_time":0.2623189527,"remaining_time":0.6391207473},
{"learn":[4.469164956],"iteration":291,"passed_time":0.262931036,"remaining_time":0.6375177174},
{"learn":[4.462068024],"iteration":292,"passed_time":0.2634982843,"remaining_time":0.6358132661},
{"learn":[4.458540976],"iteration":293,"passed_time":0.2640592381,"remaining_time":0.6341014357},
{"learn":[4.455757458],"iteration":294,"passed_time":0.2646625282,"remaining_time":0.6324985843},
{"learn":[4.453027414],"iteration":295,"passed_time":0.2652622942,"remaining_time":0.6308941051},
{"learn":[4.450659338],"iteration":296,"passed_time":0.2659717729,"remaining_time":0.629556082},
{"learn":[4.444696901],"iteration":297,"passed_time":0.2665675229,"remaining_time":0.6279543661},
{"learn":[4.442052813],"iteration":298,"passed_time":0.2671277553,"remaining_time":0.6262761087},
{"learn":[4.440036756],"iteration":299,"passed_time":0.267653926,"remaining_time":0.6245258273},
{"learn":[4.435017051],"iteration":300,"passed_time":0.2683208091,"remaining_time":0.6231104503},
{"learn":[4.429962125],"iteration":301,"passed_time":0.2689158444,"remaining_time":0.6215339714},
{"learn":[4.427666256],"iteration":302,"passed_time":0.2694909319,"remaining_time":0.6199180842},
{"learn":[4.425030004],"iteration":303,"passed_time":0.2700967475,"remaining_time":0.6183793956},
{"learn":[4.422588771],"iteration":304,"passed_time":0.2707112414,"remaining_time":0.6168665991},
{"learn":[4.418936667],"iteration":305,"passed_time":0.2713356873,"remaining_time":0.6153822451},
{"learn":[4.416887976],"iteration":306,"passed_time":0.2718964525,"remaining_time":0.6137597446},
{"learn":[4.413773354],"iteration":307,"passed_time":0.272536401,"remaining_time":0.6123220437},
{"learn":[4.411129391],"iteration":308,"passed_time":0.2734748052,"remaining_time":0.6115569269},
{"learn":[4.40850819],"iteration":309,"passed_time":0.2744522151,"remaining_time":0.610877511},
{"learn":[4.404880292],"iteration":310,"passed_time":0.2762878332,"remaining_time":0.6120974826},
{"learn":[4.404593827],"iteration":311,"passed_time":0.2786554529,"remaining_time":0.6144709986},
{"learn":[4.402139942],"iteration":312,"passed_time":0.2805670207,"remaining_time":0.6158132372},
{"learn":[4.400284725],"iteration":313,"passed_time":0.2813156383,"remaining_time":0.6145940378},
{"learn":[4.395805521],"iteration":314,"passed_time":0.2821831546,"remaining_time":0.6136363839},
{"learn":[4.392838833],"iteration":315,"passed_time":0.2828518641,"remaining_time":0.6122489718},
{"learn":[4.389213061],"iteration":316,"passed_time":0.2845309317,"remaining_time":0.6130429854},
{"learn":[4.3861981],"iteration":317,"passed_time":0.2852747617,"remaining_time":0.6118156839},
{"learn":[4.385054234],"iteration":318,"passed_time":0.2859095776,"remaining_time":0.6103586908},
{"learn":[4.379364607],"iteration":319,"passed_time":0.2867383212,"remaining_time":0.6093189326},
{"learn":[4.378387619],"iteration":320,"passed_time":0.2879751708,"remaining_time":0.6091437414},
{"learn":[4.375816727],"iteration":321,"passed_time":0.2887008653,"remaining_time":0.6078856728},
{"learn":[4.374600202],"iteration":322,"passed_time":0.2909655116,"remaining_time":0.6098565058},
{"learn":[4.37098897],"iteration":323,"passed_time":0.2925045919,"remaining_time":0.6102873584},
{"learn":[4.367418484],"iteration":324,"passed_time":0.2933736426,"remaining_time":0.6093144885},
{"learn":[4.363584638],"iteration":325,"passed_time":0.2946256903,"remaining_time":0.609134096},
{"learn":[4.360770706],"iteration":326,"passed_time":0.2956243822,"remaining_time":0.6084257163},
{"learn":[4.358675808],"iteration":327,"passed_time":0.2967886005,"remaining_time":0.6080546937},
{"learn":[4.354228195],"iteration":328,"passed_time":0.2975512673,"remaining_time":0.6068598794},
{"learn":[4.353773425],"iteration":329,"passed_time":0.2984254308,"remaining_time":0.6058940564},
{"learn":[4.351648009],"iteration":330,"passed_time":0.2992391214,"remaining_time":0.6048065625},
{"learn":[4.348209927],"iteration":331,"passed_time":0.3000124189,"remaining_time":0.6036394452},
{"learn":[4.345852733],"iteration":332,"passed_time":0.3006322968,"remaining_time":0.6021673932},
{"learn":[4.34237339],"iteration":333,"passed_time":0.3012154947,"remaining_time":0.6006273038},
{"learn":[4.340814362],"iteration":334,"passed_time":0.3021736938,"remaining_time":0.5998373326},
{"learn":[4.339707068],"iteration":335,"passed_time":0.3031002154,"remaining_time":0.5989837589},
{"learn":[4.335430786],"iteration":336,"passed_time":0.303818491,"remaining_time":0.5977200579},
{"learn":[4.33521887],"iteration":337,"passed_time":0.3049360243,"remaining_time":0.5972415625},
{"learn":[4.328507238],"iteration":338,"passed_time":0.3056697604,"remaining_time":0.5960109487},
{"learn":[4.326140732],"iteration":339,"passed_time":0.3065187814,"remaining_time":0.5950070463},
{"learn":[4.323785636],"iteration":340,"passed_time":0.307184231,"remaining_time":0.593649291},
{"learn":[4.320632534],"iteration":341,"passed_time":0.3077042888,"remaining_time":0.5920158538},
{"learn":[4.31973724],"iteration":342,"passed_time":0.3083900813,"remaining_time":0.5907063656},
{"learn":[4.318000924],"iteration":343,"passed_time":0.3090533896,"remaining_time":0.5893576268},
{"learn":[4.312713628],"iteration":344,"passed_time":0.3099652585,"remaining_time":0.5884847661},
{"learn":[4.308220789],"iteration":345,"passed_time":0.3111663308,"remaining_time":0.5881583246},
{"learn":[4.305890947],"iteration":346,"passed_time":0.3126869559,"remaining_time":0.5884281909},
{"learn":[4.305137856],"iteration":347,"passed_time":0.3137118703,"remaining_time":0.5877590215},
{"learn":[4.304787172],"iteration":348,"passed_time":0.3146370763,"remaining_time":0.5869018242},
{"learn":[4.30350134],"iteration":349,"passed_time":0.3154572551,"remaining_time":0.5858491881},
{"learn":[4.30293809],"iteration":350,"passed_time":0.3162204227,"remaining_time":0.5846924625},
{"learn":[4.299548459],"iteration":351,"passed_time":0.3168953355,"remaining_time":0.583375504},
{"learn":[4.294768408],"iteration":352,"passed_time":0.3175002973,"remaining_time":0.5819339726},
{"learn":[4.294581479],"iteration":353,"passed_time":0.3180482582,"remaining_time":0.5803931491},
{"learn":[4.292551604],"iteration":354,"passed_time":0.3185793284,"remaining_time":0.5788272305},
{"learn":[4.288628894],"iteration":355,"passed_time":0.3191996003,"remaining_time":0.5774284904},
{"learn":[4.287802767],"iteration":356,"passed_time":0.3198091677,"remaining_time":0.5760148315},
{"learn":[4.284566905],"iteration":357,"passed_time":0.3203673851,"remaining_time":0.5745135788},
{"learn":[4.27890232],"iteration":358,"passed_time":0.3209699147,"remaining_time":0.5730967001},
{"learn":[4.276938023],"iteration":359,"passed_time":0.3215002513,"remaining_time":0.5715560023},
{"learn":[4.273425094],"iteration":360,"passed_time":0.3220649547,"remaining_time":0.5700817342},
{"learn":[4.269726505],"iteration":361,"passed_time":0.3227653247,"remaining_time":0.5688515944},
{"learn":[4.265565857],"iteration":362,"passed_time":0.3233819538,"remaining_time":0.567477423},
{"learn":[4.262117173],"iteration":363,"passed_time":0.3239442124,"remaining_time":0.5660124151},
{"learn":[4.259185148],"iteration":364,"passed_time":0.3245341941,"remaining_time":0.5646005842},
{"learn":[4.257668507],"iteration":365,"passed_time":0.3252129785,"remaining_time":0.5633470721},
{"learn":[4.253432436],"iteration":366,"passed_time":0.3259167369,"remaining_time":0.5621397668},
{"learn":[4.250216667],"iteration":367,"passed_time":0.3265352497,"remaining_time":0.5607887983},
{"learn":[4.24514828],"iteration":368,"passed_time":0.327148736,"remaining_time":0.5594332043},
{"learn":[4.244015772],"iteration":369,"passed_time":0.3276441379,"remaining_time":0.5578805592},
{"learn":[4.240329192],"iteration":370,"passed_time":0.3281079746,"remaining_time":0.5562800971},
{"learn":[4.236718014],"iteration":371,"passed_time":0.328678974,"remaining_time":0.554866655},
{"learn":[4.233495944],"iteration":372,"passed_time":0.3293845037,"remaining_time":0.5536838708},
{"learn":[4.230357491],"iteration":373,"passed_time":0.3300347019,"remaining_time":0.5524110251},
{"learn":[4.227381215],"iteration":374,"passed_time":0.3306930396,"remaining_time":0.551155066},
{"learn":[4.226169067],"iteration":375,"passed_time":0.3312790265,"remaining_time":0.5497822142},
{"learn":[4.225963861],"iteration":376,"passed_time":0.3319108347,"remaining_time":0.5484892574},
{"learn":[4.224346548],"iteration":377,"passed_time":0.3324878569,"remaining_time":0.5471096482},
{"learn":[4.222595381],"iteration":378,"passed_time":0.3330199459,"remaining_time":0.5456606501},
{"learn":[4.219700938],"iteration":379,"passed_time":0.333595084,"remaining_time":0.544286716},
{"learn":[4.216356207],"iteration":380,"passed_time":0.3341892896,"remaining_time":0.5429479534},
{"learn":[4.214326494],"iteration":381,"passed_time":0.3346620817,"remaining_time":0.5414166662},
{"learn":[4.212901398],"iteration":382,"passed_time":0.3352703908,"remaining_time":0.5401092197},
{"learn":[4.211331091],"iteration":383,"passed_time":0.3359334235,"remaining_time":0.5388932002},
{"learn":[4.208624791],"iteration":384,"passed_time":0.3364959753,"remaining_time":0.537519545},
{"learn":[4.204659106],"iteration":385,"passed_time":0.3371503428,"remaining_time":0.5362961412},
{"learn":[4.202968852],"iteration":386,"passed_time":0.3377148007,"remaining_time":0.5349332631},
{"learn":[4.197261935],"iteration":387,"passed_time":0.3382692323,"remaining_time":0.5335586861},
{"learn":[4.196934403],"iteration":388,"passed_time":0.3387856454,"remaining_time":0.5321286102},
{"learn":[4.192479929],"iteration":389,"passed_time":0.3393220104,"remaining_time":0.5307344266},
{"learn":[4.190243116],"iteration":390,"passed_time":0.3398601248,"remaining_time":0.5293473555},
{"learn":[4.185852431],"iteration":391,"passed_time":0.3404054571,"remaining_time":0.527975811},
{"learn":[4.180967944],"iteration":392,"passed_time":0.3409728233,"remaining_time":0.5266425032},
{"learn":[4.178283162],"iteration":393,"passed_time":0.3415826534,"remaining_time":0.5253783959},
{"learn":[4.176341157],"iteration":394,"passed_time":0.3422295229,"remaining_time":0.5241743325},
{"learn":[4.176041504],"iteration":395,"passed_time":0.3427263275,"remaining_time":0.5227441965},
{"learn":[4.175564513],"iteration":396,"passed_time":0.3432106965,"remaining_time":0.521299874},
{"learn":[4.170830274],"iteration":397,"passed_time":0.3437486185,"remaining_time":0.5199413778},
{"learn":[4.167804808],"iteration":398,"passed_time":0.344339159,"remaining_time":0.5186662521},
{"learn":[4.165860548],"iteration":399,"passed_time":0.3448417837,"remaining_time":0.5172626756},
{"learn":[4.160950571],"iteration":400,"passed_time":0.3454220979,"remaining_time":0.5159796424},
{"learn":[4.158544115],"iteration":401,"passed_time":0.3460372599,"remaining_time":0.5147519439},
{"learn":[4.154448767],"iteration":402,"passed_time":0.3465584368,"remaining_time":0.5133880565},
{"learn":[4.15197457],"iteration":403,"passed_time":0.3471131606,"remaining_time":0.5120778309},
{"learn":[4.149562679],"iteration":404,"passed_time":0.3477460195,"remaining_time":0.5108861274},
{"learn":[4.149327961],"iteration":405,"passed_time":0.3483519237,"remaining_time":0.5096577405},
{"learn":[4.147444889],"iteration":406,"passed_time":0.3489070619,"remaining_time":0.5083584464},
{"learn":[4.147254809],"iteration":407,"passed_time":0.349486684,"remaining_time":0.5070983258},
{"learn":[4.144589165],"iteration":408,"passed_time":0.3500344246,"remaining_time":0.5057954644},
{"learn":[4.141691034],"iteration":409,"passed_time":0.3506261732,"remaining_time":0.504559615},
{"learn":[4.138893468],"iteration":410,"passed_time":0.3511787799,"remaining_time":0.5032708062},
{"learn":[4.136964597],"iteration":411,"passed_time":0.3517317829,"remaining_time":0.5019861367},
{"learn":[4.133773523],"iteration":412,"passed_time":0.3522804588,"remaining_time":0.5006988604},
{"learn":[4.131363444],"iteration":413,"passed_time":0.3527908026,"remaining_time":0.4993608945},
{"learn":[4.130228592],"iteration":414,"passed_time":0.3533089264,"remaining_time":0.4980378842},
{"learn":[4.12884186],"iteration":415,"passed_time":0.3538837765,"remaining_time":0.4967983786},
{"learn":[4.12413494],"iteration":416,"passed_time":0.3544875112,"remaining_time":0.4956024438},
{"learn":[4.119422508],"iteration":417,"passed_time":0.3551022975,"remaining_time":0.49442473},
{"learn":[4.117038244],"iteration":418,"passed_time":0.3556635501,"remaining_time":0.4931754716},
{"learn":[4.116067631],"iteration":419,"passed_time":0.356285536,"remaining_time":0.4920133593},
{"learn":[4.110343455],"iteration":420,"passed_time":0.3568418793,"remaining_time":0.4907635348},
{"learn":[4.105604544],"iteration":421,"passed_time":0.3573708185,"remaining_time":0.4894794622},
{"learn":[4.103390131],"iteration":422,"passed_time":0.3578680282,"remaining_time":0.4881556792},
{"learn":[4.096724402],"iteration":423,"passed_time":0.3583657511,"remaining_time":0.486836492},
{"learn":[4.093431279],"iteration":424,"passed_time":0.3588814591,"remaining_time":0.4855455035},
{"learn":[4.091412744],"iteration":425,"passed_time":0.3594250227,"remaining_time":0.4842956878},
{"learn":[4.091192901],"iteration":426,"passed_time":0.3600847169,"remaining_time":0.4832050182},
{"learn":[4.088994581],"iteration":427,"passed_time":0.3607483307,"remaining_time":0.4821216009},
{"learn":[4.087845355],"iteration":428,"passed_time":0.3614550529,"remaining_time":0.4810975179},
{"learn":[4.083650279],"iteration":429,"passed_time":0.3620208888,"remaining_time":0.4798881549},
{"learn":[4.079840652],"iteration":430,"passed_time":0.3625616861,"remaining_time":0.4786487225},
{"learn":[4.075707828],"iteration":431,"passed_time":0.3630611502,"remaining_time":0.4773581789},
{"learn":[4.071345409],"iteration":432,"passed_time":0.3636177383,"remaining_time":0.4761460915},
{"learn":[4.067460475],"iteration":433,"passed_time":0.3640986315,"remaining_time":0.4748383075},
{"learn":[4.064914749],"iteration":434,"passed_time":0.3646255701,"remaining_time":0.4735941313},
{"learn":[4.063823175],"iteration":435,"passed_time":0.36511447,"remaining_time":0.4723040392},
{"learn":[4.058898471],"iteration":436,"passed_time":0.365620742,"remaining_time":0.4710399948},
{"learn":[4.054120355],"iteration":437,"passed_time":0.3661897333,"remaining_time":0.4698598861},
{"learn":[4.052715901],"iteration":438,"passed_time":0.3668100711,"remaining_time":0.4687481774},
{"learn":[4.052114167],"iteration":439,"passed_time":0.3674268192,"remaining_time":0.4676341335},
{"learn":[4.051377267],"iteration":440,"passed_time":0.367933423,"remaining_time":0.466382729},
{"learn":[4.049275336],"iteration":441,"passed_time":0.3684264877,"remaining_time":0.4651176021},
{"learn":[4.047099198],"iteration":442,"passed_time":0.3689980578,"remaining_time":0.4639546686},
{"learn":[4.044348685],"iteration":443,"passed_time":0.3695163695,"remaining_time":0.4627277059},
{"learn":[4.042822379],"iteration":444,"passed_time":0.3701615625,"remaining_time":0.4616621734},
{"learn":[4.041258611],"iteration":445,"passed_time":0.3707732168,"remaining_time":0.4605568657},
{"learn":[4.040044254],"iteration":446,"passed_time":0.3713008079,"remaining_time":0.4593497691},
{"learn":[4.036860137],"iteration":447,"passed_time":0.3717862782,"remaining_time":0.4580938071},
{"learn":[4.036372284],"iteration":448,"passed_time":0.37227886,"remaining_time":0.4568500041},
{"learn":[4.03368231],"iteration":449,"passed_time":0.3728741282,"remaining_time":0.4557350456},
{"learn":[4.032439519],"iteration":450,"passed_time":0.373488068,"remaining_time":0.4546451205},
{"learn":[4.032008634],"iteration":451,"passed_time":0.3740709192,"remaining_time":0.4535196101},
{"learn":[4.030034932],"iteration":452,"passed_time":0.3745461959,"remaining_time":0.4522665986},
{"learn":[4.028173412],"iteration":453,"passed_time":0.3750939786,"remaining_time":0.4511042121},
{"learn":[4.023806097],"iteration":454,"passed_time":0.3756585466,"remaining_time":0.4499646327},
{"learn":[4.020239186],"iteration":455,"passed_time":0.376151423,"remaining_time":0.4487420485},
{"learn":[4.017384838],"iteration":456,"passed_time":0.376700375,"remaining_time":0.4475892859},
{"learn":[4.016468229],"iteration":457,"passed_time":0.377216976,"remaining_time":0.4464008755},
{"learn":[4.014530169],"iteration":458,"passed_time":0.3777729052,"remaining_time":0.4452617467},
{"learn":[4.012884822],"iteration":459,"passed_time":0.3783777267,"remaining_time":0.4441825487},
{"learn":[4.008924707],"iteration":460,"passed_time":0.3789125997,"remaining_time":0.4430236253},
{"learn":[4.008286778],"iteration":461,"passed_time":0.3796330753,"remaining_time":0.4420835379},
{"learn":[4.006444202],"iteration":462,"passed_time":0.3803201696,"remaining_time":0.4411056827},
{"learn":[4.003284363],"iteration":463,"passed_time":0.3809456488,"remaining_time":0.4400579047},
{"learn":[3.999811484],"iteration":464,"passed_time":0.3814892317,"remaining_time":0.4389177182},
{"learn":[3.997483319],"iteration":465,"passed_time":0.3821147555,"remaining_time":0.4378739903},
{"learn":[3.99708333],"iteration":466,"passed_time":0.3827707485,"remaining_time":0.4368668286},
{"learn":[3.995860263],"iteration":467,"passed_time":0.3833618765,"remaining_time":0.4357874323},
{"learn":[3.994131111],"iteration":468,"passed_time":0.3839329722,"remaining_time":0.4346874376},
{"learn":[3.993125499],"iteration":469,"passed_time":0.3844935454,"remaining_time":0.4335778278},
{"learn":[3.992954084],"iteration":470,"passed_time":0.3851240768,"remaining_time":0.4325491223},
{"learn":[3.990635743],"iteration":471,"passed_time":0.385774438,"remaining_time":0.4315442865},
{"learn":[3.986678254],"iteration":472,"passed_time":0.3864243575,"remaining_time":0.4305404575},
{"learn":[3.986393291],"iteration":473,"passed_time":0.3869525142,"remaining_time":0.429403001},
{"learn":[3.986152671],"iteration":474,"passed_time":0.3874669937,"remaining_time":0.4282529931},
{"learn":[3.985596662],"iteration":475,"passed_time":0.3880476293,"remaining_time":0.4271784827},
{"learn":[3.983853457],"iteration":476,"passed_time":0.3885834675,"remaining_time":0.4260569256},
{"learn":[3.983263928],"iteration":477,"passed_time":0.3891511693,"remaining_time":0.4249726158},
{"learn":[3.980067202],"iteration":478,"passed_time":0.3896832675,"remaining_time":0.4238517378},
{"learn":[3.978115407],"iteration":479,"passed_time":0.3902621013,"remaining_time":0.422783943},
{"learn":[3.972661644],"iteration":480,"passed_time":0.3907359247,"remaining_time":0.4216048751},
{"learn":[3.969938254],"iteration":481,"passed_time":0.3912383779,"remaining_time":0.4204595015},
{"learn":[3.968211434],"iteration":482,"passed_time":0.3918276801,"remaining_time":0.4194097529},
{"learn":[3.966113368],"iteration":483,"passed_time":0.392549827,"remaining_time":0.4185035346},
{"learn":[3.962246044],"iteration":484,"passed_time":0.3931583806,"remaining_time":0.4174774557},
{"learn":[3.961319703],"iteration":485,"passed_time":0.3937567499,"remaining_time":0.416442324},
{"learn":[3.96078191],"iteration":486,"passed_time":0.3942795892,"remaining_time":0.4153294235},
{"learn":[3.958913633],"iteration":487,"passed_time":0.3948083672,"remaining_time":0.4142251721},
{"learn":[3.957428286],"iteration":488,"passed_time":0.3953228392,"remaining_time":0.4131083249},
{"learn":[3.952641965],"iteration":489,"passed_time":0.3958421425,"remaining_time":0.4119989646},
{"learn":[3.951486786],"iteration":490,"passed_time":0.3963802446,"remaining_time":0.4109114959},
{"learn":[3.94938344],"iteration":491,"passed_time":0.3969342127,"remaining_time":0.4098426424},
{"learn":[3.947297924],"iteration":492,"passed_time":0.3975114246,"remaining_time":0.4087997815},
{"learn":[3.946284886],"iteration":493,"passed_time":0.3981563266,"remaining_time":0.4078281402},
{"learn":[3.943288204],"iteration":494,"passed_time":0.3987933429,"remaining_time":0.4068497741},
{"learn":[3.943076488],"iteration":495,"passed_time":0.3993248641,"remaining_time":0.4057655877},
{"learn":[3.942347078],"iteration":496,"passed_time":0.3998732286,"remaining_time":0.4047006721},
{"learn":[3.940251541],"iteration":497,"passed_time":0.4003334341,"remaining_time":0.4035489637},
{"learn":[3.939011019],"iteration":498,"passed_time":0.4008753122,"remaining_time":0.4024820269},
{"learn":[3.938760512],"iteration":499,"passed_time":0.4014116009,"remaining_time":0.4014116009},
{"learn":[3.934522727],"iteration":500,"passed_time":0.4019072417,"remaining_time":0.4003028216},
{"learn":[3.930091193],"iteration":501,"passed_time":0.4023790672,"remaining_time":0.3991728595},
{"learn":[3.927671752],"iteration":502,"passed_time":0.4028461096,"remaining_time":0.3980407882},
{"learn":[3.927280041],"iteration":503,"passed_time":0.403365543,"remaining_time":0.3969629153},
{"learn":[3.925987561],"iteration":504,"passed_time":0.4039268034,"remaining_time":0.3959282528},
{"learn":[3.921645957],"iteration":505,"passed_time":0.404500832,"remaining_time":0.3949079269},
{"learn":[3.920333743],"iteration":506,"passed_time":0.4050082283,"remaining_time":0.3938245692},
{"learn":[3.918659461],"iteration":507,"passed_time":0.4055549123,"remaining_time":0.3927815292},
{"learn":[3.916124385],"iteration":508,"passed_time":0.4060746404,"remaining_time":0.391714437},
{"learn":[3.913849268],"iteration":509,"passed_time":0.4065555627,"remaining_time":0.3906122073},
{"learn":[3.912826119],"iteration":510,"passed_time":0.4071586694,"remaining_time":0.3896293333},
{"learn":[3.910034145],"iteration":511,"passed_time":0.4077044842,"remaining_time":0.3885933365},
{"learn":[3.90792379],"iteration":512,"passed_time":0.4083435978,"remaining_time":0.3876478209},
{"learn":[3.907823851],"iteration":513,"passed_time":0.4088185299,"remaining_time":0.3865482598},
{"learn":[3.904527401],"iteration":514,"passed_time":0.4092878069,"remaining_time":0.3854457987},
{"learn":[3.903378283],"iteration":515,"passed_time":0.409798353,"remaining_time":0.3843845016},
{"learn":[3.902170135],"iteration":516,"passed_time":0.4103832873,"remaining_time":0.3833948313},
{"learn":[3.899435429],"iteration":517,"passed_time":0.4109272199,"remaining_time":0.3823685715},
{"learn":[3.897497505],"iteration":518,"passed_time":0.4114268299,"remaining_time":0.3813030928},
{"learn":[3.896426119],"iteration":519,"passed_time":0.4119110285,"remaining_time":0.3802255647},
{"learn":[3.896044669],"iteration":520,"passed_time":0.4124661615,"remaining_time":0.3792155304},
{"learn":[3.892795942],"iteration":521,"passed_time":0.4130170378,"remaining_time":0.3782033411},
{"learn":[3.892413888],"iteration":522,"passed_time":0.41350481,"remaining_time":0.377135362},
{"learn":[3.891738985],"iteration":523,"passed_time":0.4140718863,"remaining_time":0.3761416372},
{"learn":[3.88822057],"iteration":524,"passed_time":0.4146163153,"remaining_time":0.3751290472},
{"learn":[3.883837053],"iteration":525,"passed_time":0.4151582347,"remaining_time":0.3741159758},
{"learn":[3.881769742],"iteration":526,"passed_time":0.4156818002,"remaining_time":0.3730882192},
{"learn":[3.880356898],"iteration":527,"passed_time":0.4162212053,"remaining_time":0.372076532},
{"learn":[3.879250273],"iteration":528,"passed_time":0.4168234618,"remaining_time":0.3711225908},
{"learn":[3.877174493],"iteration":529,"passed_time":0.4173545306,"remaining_time":0.3701068479},
{"learn":[3.875854201],"iteration":530,"passed_time":0.4178797406,"remaining_time":0.3690877558},
{"learn":[3.873189396],"iteration":531,"passed_time":0.4184994752,"remaining_time":0.3681536737},
{"learn":[3.871583368],"iteration":532,"passed_time":0.4189961455,"remaining_time":0.3671129455},
{"learn":[3.869622679],"iteration":533,"passed_time":0.4195115477,"remaining_time":0.3660906016},
{"learn":[3.866860164],"iteration":534,"passed_time":0.4200012505,"remaining_time":0.3650478159},
{"learn":[3.864498444],"iteration":535,"passed_time":0.4205484334,"remaining_time":0.3640568528},
{"learn":[3.861416322],"iteration":536,"passed_time":0.421152439,"remaining_time":0.3631165349},
{"learn":[3.860265769],"iteration":537,"passed_time":0.4217045516,"remaining_time":0.3621329049},
{"learn":[3.859328725],"iteration":538,"passed_time":0.4222041749,"remaining_time":0.3611059827},
{"learn":[3.858521278],"iteration":539,"passed_time":0.4228078438,"remaining_time":0.3601696447},
{"learn":[3.85599111],"iteration":540,"passed_time":0.4234758408,"remaining_time":0.3592891145},
{"learn":[3.852379816],"iteration":541,"passed_time":0.424071477,"remaining_time":0.3583482223},
{"learn":[3.851327537],"iteration":542,"passed_time":0.4246543796,"remaining_time":0.3573978848},
{"learn":[3.847854898],"iteration":543,"passed_time":0.4252046825,"remaining_time":0.3564215721},
{"learn":[3.847083414],"iteration":544,"passed_time":0.4257358968,"remaining_time":0.3554308863},
{"learn":[3.845397429],"iteration":545,"passed_time":0.4262393962,"remaining_time":0.3544188386},
{"learn":[3.841933528],"iteration":546,"passed_time":0.426742086,"remaining_time":0.3534079798},
{"learn":[3.840996474],"iteration":547,"passed_time":0.42734714,"remaining_time":0.3524834074},
{"learn":[3.838355966],"iteration":548,"passed_time":0.4279182963,"remaining_time":0.3515321524},
{"learn":[3.83342799],"iteration":549,"passed_time":0.4284632878,"remaining_time":0.3505608719},
{"learn":[3.828161535],"iteration":550,"passed_time":0.4289593468,"remaining_time":0.3495512645},
{"learn":[3.823502399],"iteration":551,"passed_time":0.4295546939,"remaining_time":0.3486240994},
{"learn":[3.820068862],"iteration":552,"passed_time":0.4300979081,"remaining_time":0.3476559944},
{"learn":[3.817951642],"iteration":553,"passed_time":0.430570945,"remaining_time":0.3466329268},
{"learn":[3.815785958],"iteration":554,"passed_time":0.4310939595,"remaining_time":0.3456519135},
{"learn":[3.81503012],"iteration":555,"passed_time":0.4316139648,"remaining_time":0.3446701445},
{"learn":[3.813529315],"iteration":556,"passed_time":0.4320828108,"remaining_time":0.3436493451},
{"learn":[3.808881326],"iteration":557,"passed_time":0.4326151885,"remaining_time":0.3426808482},
{"learn":[3.808740434],"iteration":558,"passed_time":0.4331211654,"remaining_time":0.341693084},
{"learn":[3.80714352],"iteration":559,"passed_time":0.4336890451,"remaining_time":0.3407556783},
{"learn":[3.80573346],"iteration":560,"passed_time":0.4342498966,"remaining_time":0.3398140902},
{"learn":[3.803370052],"iteration":561,"passed_time":0.4347534856,"remaining_time":0.338829229},
{"learn":[3.803215211],"iteration":562,"passed_time":0.4352752883,"remaining_time":0.3378602149},
{"learn":[3.801309667],"iteration":563,"passed_time":0.4358098697,"remaining_time":0.3369026652},
{"learn":[3.800003847],"iteration":564,"passed_time":0.4362802985,"remaining_time":0.335897221},
{"learn":[3.798026138],"iteration":565,"passed_time":0.4367783056,"remaining_time":0.3349148138},
{"learn":[3.794745847],"iteration":566,"passed_time":0.4372368847,"remaining_time":0.3339040055},
{"learn":[3.794312041],"iteration":567,"passed_time":0.4377224395,"remaining_time":0.3329156582},
{"learn":[3.792205926],"iteration":568,"passed_time":0.4382630545,"remaining_time":0.3319707847},
{"learn":[3.788991061],"iteration":569,"passed_time":0.4387965569,"remaining_time":0.3310219639},
{"learn":[3.787391572],"iteration":570,"passed_time":0.4393273191,"remaining_time":0.3300725392},
{"learn":[3.7826445],"iteration":571,"passed_time":0.4398844578,"remaining_time":0.3291443146},
{"learn":[3.781700331],"iteration":572,"passed_time":0.4403978279,"remaining_time":0.3281847688},
{"learn":[3.780045374],"iteration":573,"passed_time":0.4409823187,"remaining_time":0.3272795606},
{"learn":[3.775462644],"iteration":574,"passed_time":0.4415595336,"remaining_time":0.3263700901},
{"learn":[3.773711943],"iteration":575,"passed_time":0.4421616097,"remaining_time":0.3254800738},
{"learn":[3.772415806],"iteration":576,"passed_time":0.4427355613,"remaining_time":0.3245704375},
{"learn":[3.770170875],"iteration":577,"passed_time":0.4432710579,"remaining_time":0.3236338866},
{"learn":[3.765166479],"iteration":578,"passed_time":0.4437681952,"remaining_time":0.3226708293},
{"learn":[3.763976102],"iteration":579,"passed_time":0.4442930737,"remaining_time":0.3217294671},
{"learn":[3.760761708],"iteration":580,"passed_time":0.4448365751,"remaining_time":0.3208029689},
{"learn":[3.758155662],"iteration":581,"passed_time":0.4453995309,"remaining_time":0.3198917593},
{"learn":[3.756844548],"iteration":582,"passed_time":0.4458798118,"remaining_time":0.3189226098},
{"learn":[3.753098923],"iteration":583,"passed_time":0.4464313764,"remaining_time":0.3180059119},
{"learn":[3.751618946],"iteration":584,"passed_time":0.4469872118,"remaining_time":0.3170934921},
{"learn":[3.751398464],"iteration":585,"passed_time":0.4475347113,"remaining_time":0.3161764002},
{"learn":[3.749920103],"iteration":586,"passed_time":0.4480482521,"remaining_time":0.3152366748},
{"learn":[3.748237465],"iteration":587,"passed_time":0.4485717462,"remaining_time":0.3143053732},
{"learn":[3.746021536],"iteration":588,"passed_time":0.4491606035,"remaining_time":0.3134210663},
{"learn":[3.74417648],"iteration":589,"passed_time":0.4496902466,"remaining_time":0.312496612},
{"learn":[3.738788389],"iteration":590,"passed_time":0.4503363194,"remaining_time":0.3116540688},
{"learn":[3.736021611],"iteration":591,"passed_time":0.450873939,"remaining_time":0.3107374444},
{"learn":[3.734546151],"iteration":592,"passed_time":0.4514264315,"remaining_time":0.3098323063},
{"learn":[3.733527479],"iteration":593,"passed_time":0.4519853308,"remaining_time":0.3089327345},
{"learn":[3.733026392],"iteration":594,"passed_time":0.4524683999,"remaining_time":0.3079826924},
{"learn":[3.730314752],"iteration":595,"passed_time":0.4529383033,"remaining_time":0.3070252929},
{"learn":[3.727342596],"iteration":596,"passed_time":0.4535027987,"remaining_time":0.3061333801},
{"learn":[3.725459604],"iteration":597,"passed_time":0.4539820981,"remaining_time":0.30518529},
{"learn":[3.723158842],"iteration":598,"passed_time":0.4544904104,"remaining_time":0.3042581879},
{"learn":[3.722362756],"iteration":599,"passed_time":0.4549774768,"remaining_time":0.3033183179},
{"learn":[3.721443615],"iteration":600,"passed_time":0.455450696,"remaining_time":0.3023707616},
{"learn":[3.720743486],"iteration":601,"passed_time":0.4559968748,"remaining_time":0.3014730169},
{"learn":[3.720215334],"iteration":602,"passed_time":0.4565015037,"remaining_time":0.3005490829},
{"learn":[3.719436563],"iteration":603,"passed_time":0.4570443663,"remaining_time":0.2996516044},
{"learn":[3.715046574],"iteration":604,"passed_time":0.4575353665,"remaining_time":0.2987214376},
{"learn":[3.71443396],"iteration":605,"passed_time":0.458017806,"remaining_time":0.2977871544},
{"learn":[3.712938941],"iteration":606,"passed_time":0.4585758406,"remaining_time":0.2969033037},
{"learn":[3.712814764],"iteration":607,"passed_time":0.4590490223,"remaining_time":0.295965817},
{"learn":[3.71235348],"iteration":608,"passed_time":0.4596261836,"remaining_time":0.2950966138},
{"learn":[3.711223749],"iteration":609,"passed_time":0.4601224726,"remaining_time":0.2941766628},
{"learn":[3.710755648],"iteration":610,"passed_time":0.4606416932,"remaining_time":0.2932726983},
{"learn":[3.708668039],"iteration":611,"passed_time":0.4611891644,"remaining_time":0.2923879016},
{"learn":[3.705623591],"iteration":612,"passed_time":0.4617021833,"remaining_time":0.291482455},
{"learn":[3.704045802],"iteration":613,"passed_time":0.4622651689,"remaining_time":0.290609699},
{"learn":[3.699915209],"iteration":614,"passed_time":0.4627655162,"remaining_time":0.2896987378},
{"learn":[3.696182221],"iteration":615,"passed_time":0.4633367935,"remaining_time":0.2888333258},
{"learn":[3.694263278],"iteration":616,"passed_time":0.4638528725,"remaining_time":0.2879346032},
{"learn":[3.693810229],"iteration":617,"passed_time":0.4643563934,"remaining_time":0.2870293565},
{"learn":[3.690900932],"iteration":618,"passed_time":0.4649222528,"remaining_time":0.2861637776},
{"learn":[3.688020895],"iteration":619,"passed_time":0.465413429,"remaining_time":0.2852533919},
{"learn":[3.685491894],"iteration":620,"passed_time":0.4659865047,"remaining_time":0.2843943403},
{"learn":[3.684328128],"iteration":621,"passed_time":0.4665030592,"remaining_time":0.2835018591},
{"learn":[3.680640153],"iteration":622,"passed_time":0.467021183,"remaining_time":0.2826115345},
{"learn":[3.678932783],"iteration":623,"passed_time":0.4675599035,"remaining_time":0.2817348137},
{"learn":[3.674167041],"iteration":624,"passed_time":0.4680875482,"remaining_time":0.2808525289},
{"learn":[3.672200976],"iteration":625,"passed_time":0.4686456562,"remaining_time":0.2799895773},
{"learn":[3.670606604],"iteration":626,"passed_time":0.4691667323,"remaining_time":0.279105568},
{"learn":[3.665506042],"iteration":627,"passed_time":0.4697175401,"remaining_time":0.2782403263},
{"learn":[3.664214007],"iteration":628,"passed_time":0.4702363452,"remaining_time":0.2773572084},
{"learn":[3.66261643],"iteration":629,"passed_time":0.470711284,"remaining_time":0.2764494843},
{"learn":[3.662118449],"iteration":630,"passed_time":0.4712003421,"remaining_time":0.2755513886},
{"learn":[3.660871366],"iteration":631,"passed_time":0.471722919,"remaining_time":0.2746741047},
{"learn":[3.656695243],"iteration":632,"passed_time":0.4722636151,"remaining_time":0.2738084467},
{"learn":[3.654497801],"iteration":633,"passed_time":0.4727924478,"remaining_time":0.2729369651},
{"learn":[3.654189134],"iteration":634,"passed_time":0.4732815003,"remaining_time":0.272043697},
{"learn":[3.653957699],"iteration":635,"passed_time":0.4737407123,"remaining_time":0.2711346215},
{"learn":[3.651920725],"iteration":636,"passed_time":0.4742690643,"remaining_time":0.2702663585},
{"learn":[3.65106705],"iteration":637,"passed_time":0.4747791227,"remaining_time":0.2693887812},
{"learn":[3.650612844],"iteration":638,"passed_time":0.475311084,"remaining_time":0.2685247282},
{"learn":[3.649884732],"iteration":639,"passed_time":0.4758978273,"remaining_time":0.2676925278},
{"learn":[3.646276182],"iteration":640,"passed_time":0.4765214183,"remaining_time":0.2668817304},
{"learn":[3.645808194],"iteration":641,"passed_time":0.4771168803,"remaining_time":0.2660558305},
{"learn":[3.645042989],"iteration":642,"passed_time":0.4776057493,"remaining_time":0.2651714658},
{"learn":[3.639864499],"iteration":643,"passed_time":0.4781588293,"remaining_time":0.2643238249},
{"learn":[3.637318478],"iteration":644,"passed_time":0.478724272,"remaining_time":0.2634839017},
{"learn":[3.636344905],"iteration":645,"passed_time":0.4792662725,"remaining_time":0.2626319822},
{"learn":[3.634754643],"iteration":646,"passed_time":0.4798210078,"remaining_time":0.2617879687},
{"learn":[3.630724975],"iteration":647,"passed_time":0.4804162492,"remaining_time":0.2609668514},
{"learn":[3.629408252],"iteration":648,"passed_time":0.4809560606,"remaining_time":0.2601164519},
{"learn":[3.62790646],"iteration":649,"passed_time":0.4814632098,"remaining_time":0.2592494207},
{"learn":[3.627388973],"iteration":650,"passed_time":0.4819832724,"remaining_time":0.2583904179},
{"learn":[3.625163557],"iteration":651,"passed_time":0.48245285,"remaining_time":0.2575055089},
{"learn":[3.623701985],"iteration":652,"passed_time":0.4830005017,"remaining_time":0.25666336},
{"learn":[3.622342639],"iteration":653,"passed_time":0.4835350492,"remaining_time":0.2558151789},
{"learn":[3.621130639],"iteration":654,"passed_time":0.4840512535,"remaining_time":0.2549582938},
{"learn":[3.619125665],"iteration":655,"passed_time":0.4846972386,"remaining_time":0.2541705032},
{"learn":[3.618878783],"iteration":656,"passed_time":0.4852797389,"remaining_time":0.2533500007},
{"learn":[3.616207429],"iteration":657,"passed_time":0.4858295713,"remaining_time":0.2525132422},
{"learn":[3.61206486],"iteration":658,"passed_time":0.4863864321,"remaining_time":0.2516809914},
{"learn":[3.611955873],"iteration":659,"passed_time":0.4869328445,"remaining_time":0.2508441926},
{"learn":[3.610713743],"iteration":660,"passed_time":0.4874234208,"remaining_time":0.2499796364},
{"learn":[3.610044025],"iteration":661,"passed_time":0.4879367775,"remaining_time":0.2491278411},
{"learn":[3.607342669],"iteration":662,"passed_time":0.4884675296,"remaining_time":0.2482859087},
{"learn":[3.602510618],"iteration":663,"passed_time":0.4890674839,"remaining_time":0.2474799316},
{"learn":[3.600492392],"iteration":664,"passed_time":0.4895752724,"remaining_time":0.2466281447},
{"learn":[3.597171065],"iteration":665,"passed_time":0.4900445269,"remaining_time":0.2457580661},
{"learn":[3.594358798],"iteration":666,"passed_time":0.4905997515,"remaining_time":0.2449321098},
{"learn":[3.593945251],"iteration":667,"passed_time":0.4910634468,"remaining_time":0.2440614735},
{"learn":[3.593607748],"iteration":668,"passed_time":0.4915620912,"remaining_time":0.2432093456},
{"learn":[3.592238714],"iteration":669,"passed_time":0.4920994764,"remaining_time":0.242377354},
{"learn":[3.590144654],"iteration":670,"passed_time":0.4926193209,"remaining_time":0.2415376402},
{"learn":[3.587151536],"iteration":671,"passed_time":0.4931634671,"remaining_time":0.2407107399},
{"learn":[3.586070865],"iteration":672,"passed_time":0.4937218787,"remaining_time":0.2398916112},
{"learn":[3.585102746],"iteration":673,"passed_time":0.4942390787,"remaining_time":0.2390533229},
{"learn":[3.584362847],"iteration":674,"passed_time":0.4947792345,"remaining_time":0.2382270389},
{"learn":[3.581407561],"iteration":675,"passed_time":0.4953430569,"remaining_time":0.2374129444},
{"learn":[3.57919422],"iteration":676,"passed_time":0.4959157048,"remaining_time":0.2366038001},
{"learn":[3.577632204],"iteration":677,"passed_time":0.4965374657,"remaining_time":0.2358186784},
{"learn":[3.573911195],"iteration":678,"passed_time":0.4970362433,"remaining_time":0.2349758971},
{"learn":[3.573408216],"iteration":679,"passed_time":0.497554808,"remaining_time":0.2341434391},
{"learn":[3.571076482],"iteration":680,"passed_time":0.4981271568,"remaining_time":0.2333370969},
{"learn":[3.568177107],"iteration":681,"passed_time":0.4986543975,"remaining_time":0.2325104082},
{"learn":[3.564824621],"iteration":682,"passed_time":0.4991346776,"remaining_time":0.2316628006},
{"learn":[3.562475026],"iteration":683,"passed_time":0.4996129612,"remaining_time":0.2308153447},
{"learn":[3.561226889],"iteration":684,"passed_time":0.5001693767,"remaining_time":0.2300048959},
{"learn":[3.559383467],"iteration":685,"passed_time":0.5006797015,"remaining_time":0.2291740908},
{"learn":[3.555209766],"iteration":686,"passed_time":0.5011990203,"remaining_time":0.2283483164},
{"learn":[3.55345383],"iteration":687,"passed_time":0.5017411645,"remaining_time":0.2275337839},
{"learn":[3.552300968],"iteration":688,"passed_time":0.5022614157,"remaining_time":0.2267101601},
{"learn":[3.551253986],"iteration":689,"passed_time":0.5027582642,"remaining_time":0.2258769013},
{"learn":[3.549807725],"iteration":690,"passed_time":0.5032714583,"remaining_time":0.2250519256},
{"learn":[3.547992926],"iteration":691,"passed_time":0.5037950349,"remaining_time":0.2242324722},
{"learn":[3.545438607],"iteration":692,"passed_time":0.5043686658,"remaining_time":0.2234360468},
{"learn":[3.543313763],"iteration":693,"passed_time":0.504954828,"remaining_time":0.2226457887},
{"learn":[3.542962896],"iteration":694,"passed_time":0.5054284334,"remaining_time":0.2218067226},
{"learn":[3.539800465],"iteration":695,"passed_time":0.5059619328,"remaining_time":0.2209948672},
{"learn":[3.53953187],"iteration":696,"passed_time":0.5064918303,"remaining_time":0.2201822447},
{"learn":[3.536332425],"iteration":697,"passed_time":0.5070197626,"remaining_time":0.2193695821},
{"learn":[3.534993327],"iteration":698,"passed_time":0.5075522482,"remaining_time":0.2185596949},
{"learn":[3.531637011],"iteration":699,"passed_time":0.5081464181,"remaining_time":0.2177770363},
{"learn":[3.531040284],"iteration":700,"passed_time":0.5086353068,"remaining_time":0.2169500096},
{"learn":[3.529973872],"iteration":701,"passed_time":0.5091407662,"remaining_time":0.2161309805},
{"learn":[3.527325183],"iteration":702,"passed_time":0.5096890921,"remaining_time":0.2153309536},
{"learn":[3.527200815],"iteration":703,"passed_time":0.5101710353,"remaining_time":0.2145037307},
{"learn":[3.523459911],"iteration":704,"passed_time":0.5107114125,"remaining_time":0.2137019386},
{"learn":[3.522729934],"iteration":705,"passed_time":0.5113625982,"remaining_time":0.212947031},
{"learn":[3.522260582],"iteration":706,"passed_time":0.5120488781,"remaining_time":0.2122069608},
{"learn":[3.518641591],"iteration":707,"passed_time":0.5126575459,"remaining_time":0.211435033},
{"learn":[3.516856405],"iteration":708,"passed_time":0.513204055,"remaining_time":0.2106380536},
{"learn":[3.515083413],"iteration":709,"passed_time":0.5137166009,"remaining_time":0.2098279074},
{"learn":[3.514671214],"iteration":710,"passed_time":0.5142705783,"remaining_time":0.209035439},
{"learn":[3.512617621],"iteration":711,"passed_time":0.5148442877,"remaining_time":0.208251622},
{"learn":[3.510747971],"iteration":712,"passed_time":0.5154012352,"remaining_time":0.2074616473},
{"learn":[3.508149266],"iteration":713,"passed_time":0.5159235257,"remaining_time":0.2066584431},
{"learn":[3.504557165],"iteration":714,"passed_time":0.5164572826,"remaining_time":0.2058605952},
{"learn":[3.501367208],"iteration":715,"passed_time":0.516976937,"remaining_time":0.2050578912},
{"learn":[3.497593362],"iteration":716,"passed_time":0.5175157516,"remaining_time":0.2042635394},
{"learn":[3.496291169],"iteration":717,"passed_time":0.5180127456,"remaining_time":0.2034534739},
{"learn":[3.49330374],"iteration":718,"passed_time":0.5185516986,"remaining_time":0.2026606778},
{"learn":[3.490044385],"iteration":719,"passed_time":0.5191051306,"remaining_time":0.2018742175},
{"learn":[3.488891789],"iteration":720,"passed_time":0.5196144073,"remaining_time":0.2010713171},
{"learn":[3.486869081],"iteration":721,"passed_time":0.5201364667,"remaining_time":0.200274152},
{"learn":[3.486303638],"iteration":722,"passed_time":0.5206961738,"remaining_time":0.1994921717},
{"learn":[3.486035862],"iteration":723,"passed_time":0.5213671893,"remaining_time":0.1987532379},
{"learn":[3.482668951],"iteration":724,"passed_time":0.5219892489,"remaining_time":0.197995922},
{"learn":[3.47820549],"iteration":725,"passed_time":0.5225340704,"remaining_time":0.1972098282},
{"learn":[3.474392283],"iteration":726,"passed_time":0.5230966962,"remaining_time":0.196431084},
{"learn":[3.472268163],"iteration":727,"passed_time":0.5238092701,"remaining_time":0.195708958},
{"learn":[3.471209164],"iteration":728,"passed_time":0.524402323,"remaining_time":0.1949424274},
{"learn":[3.470049971],"iteration":729,"passed_time":0.5250221786,"remaining_time":0.1941862852},
{"learn":[3.469078654],"iteration":730,"passed_time":0.5255973148,"remaining_time":0.1934140598},
{"learn":[3.468643292],"iteration":731,"passed_time":0.5261457326,"remaining_time":0.1926325906},
{"learn":[3.468134848],"iteration":732,"passed_time":0.5267503465,"remaining_time":0.1918722272},
{"learn":[3.467820182],"iteration":733,"passed_time":0.527332967,"remaining_time":0.1911043177},
{"learn":[3.465776156],"iteration":734,"passed_time":0.5279780301,"remaining_time":0.1903594258},
{"learn":[3.463037608],"iteration":735,"passed_time":0.5286063682,"remaining_time":0.189608806},
{"learn":[3.45965637],"iteration":736,"passed_time":0.5291904531,"remaining_time":0.1888427261},
{"learn":[3.457275091],"iteration":737,"passed_time":0.5297950927,"remaining_time":0.1880844367},
{"learn":[3.455522955],"iteration":738,"passed_time":0.5303720654,"remaining_time":0.1873167917},
{"learn":[3.451270508],"iteration":739,"passed_time":0.5308890265,"remaining_time":0.1865285769},
{"learn":[3.450978947],"iteration":740,"passed_time":0.5314419149,"remaining_time":0.1857536518},
{"learn":[3.450608492],"iteration":741,"passed_time":0.5319937749,"remaining_time":0.1849789676},
{"learn":[3.448122004],"iteration":742,"passed_time":0.5325776891,"remaining_time":0.1842159705},
{"learn":[3.445646714],"iteration":743,"passed_time":0.5331499263,"remaining_time":0.183449437},
{"learn":[3.44411263],"iteration":744,"passed_time":0.5337907241,"remaining_time":0.1827068921},
{"learn":[3.443264164],"iteration":745,"passed_time":0.5344794239,"remaining_time":0.1819809298},
{"learn":[3.439521363],"iteration":746,"passed_time":0.5350628194,"remaining_time":0.181219402},
{"learn":[3.436809225],"iteration":747,"passed_time":0.5356789447,"remaining_time":0.1804693771},
{"learn":[3.435509465],"iteration":748,"passed_time":0.5362584775,"remaining_time":0.1797074471},
{"learn":[3.434450277],"iteration":749,"passed_time":0.5368924656,"remaining_time":0.1789641552},
{"learn":[3.431786753],"iteration":750,"passed_time":0.537445501,"remaining_time":0.1781943139},
{"learn":[3.430150302],"iteration":751,"passed_time":0.5379712899,"remaining_time":0.1774160637},
{"learn":[3.42696281],"iteration":752,"passed_time":0.5385043826,"remaining_time":0.1766408798},
{"learn":[3.426870334],"iteration":753,"passed_time":0.5389503033,"remaining_time":0.1758378974},
{"learn":[3.425200309],"iteration":754,"passed_time":0.5395139553,"remaining_time":0.175074065},
{"learn":[3.423383783],"iteration":755,"passed_time":0.5400576833,"remaining_time":0.1743043316},
{"learn":[3.422752979],"iteration":756,"passed_time":0.5406266516,"remaining_time":0.1735432977},
{"learn":[3.420845924],"iteration":757,"passed_time":0.5411551651,"remaining_time":0.1727698548},
{"learn":[3.418917862],"iteration":758,"passed_time":0.5417294668,"remaining_time":0.1720115962},
{"learn":[3.417095735],"iteration":759,"passed_time":0.5422318042,"remaining_time":0.1712310961},
{"learn":[3.414391848],"iteration":760,"passed_time":0.5428897368,"remaining_time":0.1705001933},
{"learn":[3.41426711],"iteration":761,"passed_time":0.5434890708,"remaining_time":0.1697511796},
{"learn":[3.411976013],"iteration":762,"passed_time":0.5440612194,"remaining_time":0.168994114},
{"learn":[3.408614844],"iteration":763,"passed_time":0.5446439888,"remaining_time":0.1682408133},
{"learn":[3.407906721],"iteration":764,"passed_time":0.5451292157,"remaining_time":0.1674579944},
{"learn":[3.407494015],"iteration":765,"passed_time":0.5456560609,"remaining_time":0.1666886661},
{"learn":[3.406287128],"iteration":766,"passed_time":0.5461475206,"remaining_time":0.1659092207},
{"learn":[3.404600442],"iteration":767,"passed_time":0.5466141328,"remaining_time":0.1651230193},
{"learn":[3.404012662],"iteration":768,"passed_time":0.5471545119,"remaining_time":0.1643598079},
{"learn":[3.400398762],"iteration":769,"passed_time":0.5476174214,"remaining_time":0.163574035},
{"learn":[3.399737714],"iteration":770,"passed_time":0.5480615622,"remaining_time":0.162783525},
{"learn":[3.399185251],"iteration":771,"passed_time":0.5486559736,"remaining_time":0.1620382927},
{"learn":[3.397245411],"iteration":772,"passed_time":0.5491608466,"remaining_time":0.1612671568},
{"learn":[3.396229831],"iteration":773,"passed_time":0.5496373674,"remaining_time":0.1604884303},
{"learn":[3.394002836],"iteration":774,"passed_time":0.5501365421,"remaining_time":0.1597170606},
{"learn":[3.389617243],"iteration":775,"passed_time":0.5506894115,"remaining_time":0.158961892},
{"learn":[3.385426488],"iteration":776,"passed_time":0.5512678914,"remaining_time":0.1582145943},
{"learn":[3.385072258],"iteration":777,"passed_time":0.5517357161,"remaining_time":0.1574361555},
{"learn":[3.383842366],"iteration":778,"passed_time":0.5522793135,"remaining_time":0.1566800106},
{"learn":[3.380110746],"iteration":779,"passed_time":0.5528853717,"remaining_time":0.1559420279},
{"learn":[3.378595218],"iteration":780,"passed_time":0.5534115539,"remaining_time":0.155181985},
{"learn":[3.377371219],"iteration":781,"passed_time":0.5539467622,"remaining_time":0.1544250565},
{"learn":[3.375814782],"iteration":782,"passed_time":0.5544794527,"remaining_time":0.1536679965},
{"learn":[3.374195887],"iteration":783,"passed_time":0.5549726302,"remaining_time":0.1529006226},
{"learn":[3.373704309],"iteration":784,"passed_time":0.5554635779,"remaining_time":0.1521333366},
{"learn":[3.372971757],"iteration":785,"passed_time":0.555951442,"remaining_time":0.1513659142},
{"learn":[3.371565136],"iteration":786,"passed_time":0.5565386083,"remaining_time":0.1506260782},
{"learn":[3.3700309],"iteration":787,"passed_time":0.5570724012,"remaining_time":0.1498722704},
{"learn":[3.368186663],"iteration":788,"passed_time":0.5575575877,"remaining_time":0.1491060215},
{"learn":[3.366710398],"iteration":789,"passed_time":0.55802848,"remaining_time":0.1483366846},
{"learn":[3.364598042],"iteration":790,"passed_time":0.5585331287,"remaining_time":0.1475770214},
{"learn":[3.36348442],"iteration":791,"passed_time":0.5590735792,"remaining_time":0.1468274046},
{"learn":[3.362001759],"iteration":792,"passed_time":0.5595445323,"remaining_time":0.1460601742},
{"learn":[3.361580401],"iteration":793,"passed_time":0.5601530315,"remaining_time":0.1453293759},
{"learn":[3.359543675],"iteration":794,"passed_time":0.5607403102,"remaining_time":0.1445934133},
{"learn":[3.35766119],"iteration":795,"passed_time":0.5612692605,"remaining_time":0.1438428758},
{"learn":[3.354592969],"iteration":796,"passed_time":0.5617504599,"remaining_time":0.143080732},
{"learn":[3.350985986],"iteration":797,"passed_time":0.5623028925,"remaining_time":0.1423373237},
{"learn":[3.349589624],"iteration":798,"passed_time":0.5628737624,"remaining_time":0.1415990316},
{"learn":[3.349110856],"iteration":799,"passed_time":0.5634636365,"remaining_time":0.1408659091},
{"learn":[3.345315441],"iteration":800,"passed_time":0.5640218137,"remaining_time":0.1401252696},
{"learn":[3.34397474],"iteration":801,"passed_time":0.564516393,"remaining_time":0.1393693838},
{"learn":[3.343800902],"iteration":802,"passed_time":0.5650096267,"remaining_time":0.1386138187},
{"learn":[3.342329465],"iteration":803,"passed_time":0.5655161564,"remaining_time":0.1378621476},
{"learn":[3.34220347],"iteration":804,"passed_time":0.5660063143,"remaining_time":0.1371071196},
{"learn":[3.341279219],"iteration":805,"passed_time":0.5665005599,"remaining_time":0.1363537328},
{"learn":[3.337329521],"iteration":806,"passed_time":0.5670381437,"remaining_time":0.1356113528},
{"learn":[3.336708453],"iteration":807,"passed_time":0.5675281137,"remaining_time":0.1348581656},
{"learn":[3.333252703],"iteration":808,"passed_time":0.5680638328,"remaining_time":0.1341164302},
{"learn":[3.332186769],"iteration":809,"passed_time":0.5685820154,"remaining_time":0.13337109},
{"learn":[3.330594851],"iteration":810,"passed_time":0.5691365028,"remaining_time":0.1326347707},
{"learn":[3.327867442],"iteration":811,"passed_time":0.5697497477,"remaining_time":0.1319125032},
{"learn":[3.327563111],"iteration":812,"passed_time":0.5702865283,"remaining_time":0.1311729161},
{"learn":[3.326308994],"iteration":813,"passed_time":0.5709001016,"remaining_time":0.1304513746},
{"learn":[3.326249879],"iteration":814,"passed_time":0.5714395123,"remaining_time":0.1297132635},
{"learn":[3.322336238],"iteration":815,"passed_time":0.5720222746,"remaining_time":0.1289854149},
{"learn":[3.320491154],"iteration":816,"passed_time":0.5726383742,"remaining_time":0.1282653886},
{"learn":[3.320434271],"iteration":817,"passed_time":0.5731671864,"remaining_time":0.1275261955},
{"learn":[3.319609638],"iteration":818,"passed_time":0.5737167836,"remaining_time":0.1267921097},
{"learn":[3.316182682],"iteration":819,"passed_time":0.574193047,"remaining_time":0.1260423762},
{"learn":[3.313126612],"iteration":820,"passed_time":0.5747600586,"remaining_time":0.1253130944},
{"learn":[3.311222803],"iteration":821,"passed_time":0.5753199368,"remaining_time":0.1245826627},
{"learn":[3.309627335],"iteration":822,"passed_time":0.5757998657,"remaining_time":0.1238354511},
{"learn":[3.307974895],"iteration":823,"passed_time":0.5763472722,"remaining_time":0.1231033009},
{"learn":[3.307321505],"iteration":824,"passed_time":0.5768422999,"remaining_time":0.1223604879},
{"learn":[3.306759087],"iteration":825,"passed_time":0.5773526578,"remaining_time":0.1216215042},
{"learn":[3.30484037],"iteration":826,"passed_time":0.5779289492,"remaining_time":0.120896866},
{"learn":[3.30201994],"iteration":827,"passed_time":0.5784219455,"remaining_time":0.1201552834},
{"learn":[3.299302297],"iteration":828,"passed_time":0.5789515763,"remaining_time":0.1194218571},
{"learn":[3.298132671],"iteration":829,"passed_time":0.5794805641,"remaining_time":0.1186887902},
{"learn":[3.296976183],"iteration":830,"passed_time":0.5799808586,"remaining_time":0.1179503792},
{"learn":[3.293144745],"iteration":831,"passed_time":0.5805254803,"remaining_time":0.1172214912},
{"learn":[3.290284404],"iteration":832,"passed_time":0.5810790752,"remaining_time":0.1164948446},
{"learn":[3.288285745],"iteration":833,"passed_time":0.5816705045,"remaining_time":0.1157761436},
{"learn":[3.286662667],"iteration":834,"passed_time":0.5822455265,"remaining_time":0.1150545052},
{"learn":[3.285692682],"iteration":835,"passed_time":0.582795508,"remaining_time":0.1143283054},
{"learn":[3.284565611],"iteration":836,"passed_time":0.5833049064,"remaining_time":0.1135946233},
{"learn":[3.283897383],"iteration":837,"passed_time":0.5837828425,"remaining_time":0.1128553944},
{"learn":[3.280712855],"iteration":838,"passed_time":0.5843105609,"remaining_time":0.1121263413},
{"learn":[3.280468341],"iteration":839,"passed_time":0.5848667305,"remaining_time":0.1114031868},
{"learn":[3.277814895],"iteration":840,"passed_time":0.5854913923,"remaining_time":0.1106933786},
{"learn":[3.276316385],"iteration":841,"passed_time":0.586041245,"remaining_time":0.1099697348},
{"learn":[3.27557063],"iteration":842,"passed_time":0.5866013331,"remaining_time":0.1092484096},
{"learn":[3.27499628],"iteration":843,"passed_time":0.5871227332,"remaining_time":0.1085203156},
{"learn":[3.273569958],"iteration":844,"passed_time":0.5876707953,"remaining_time":0.1077976015},
{"learn":[3.269665595],"iteration":845,"passed_time":0.5882179972,"remaining_time":0.1070751437},
{"learn":[3.267984685],"iteration":846,"passed_time":0.5888238548,"remaining_time":0.1063636951},
{"learn":[3.267702508],"iteration":847,"passed_time":0.5893680081,"remaining_time":0.1056414354},
{"learn":[3.266671924],"iteration":848,"passed_time":0.5899095045,"remaining_time":0.1049191227},
{"learn":[3.265359825],"iteration":849,"passed_time":0.5904908392,"remaining_time":0.1042042657},
{"learn":[3.2618983],"iteration":850,"passed_time":0.5910795644,"remaining_time":0.1034910166},
{"learn":[3.260456253],"iteration":851,"passed_time":0.5915934166,"remaining_time":0.1027650536},
{"learn":[3.258389147],"iteration":852,"passed_time":0.5921875783,"remaining_time":0.1020534279},
{"learn":[3.258108469],"iteration":853,"passed_time":0.5927184157,"remaining_time":0.1013312514},
{"learn":[3.256424936],"iteration":854,"passed_time":0.5932050051,"remaining_time":0.1006020184},
{"learn":[3.254817983],"iteration":855,"passed_time":0.5937231777,"remaining_time":0.0998786654},
{"learn":[3.253898449],"iteration":856,"passed_time":0.5942623126,"remaining_time":0.09915928903},
{"learn":[3.253023652],"iteration":857,"passed_time":0.5947483239,"remaining_time":0.09843154078},
{"learn":[3.252845542],"iteration":858,"passed_time":0.5952697173,"remaining_time":0.09771016314},
{"learn":[3.252316026],"iteration":859,"passed_time":0.5958122108,"remaining_time":0.09699268548},
{"learn":[3.24975301],"iteration":860,"passed_time":0.5962970434,"remaining_time":0.09626630549},
{"learn":[3.249151075],"iteration":861,"passed_time":0.5968610462,"remaining_time":0.09555316053},
{"learn":[3.246257135],"iteration":862,"passed_time":0.5973868664,"remaining_time":0.09483429976},
{"learn":[3.243826471],"iteration":863,"passed_time":0.5979104412,"remaining_time":0.09411553241},
{"learn":[3.243190653],"iteration":864,"passed_time":0.5984173568,"remaining_time":0.09339461638},
{"learn":[3.24008797],"iteration":865,"passed_time":0.5989215858,"remaining_time":0.09267377886},
{"learn":[3.240036811],"iteration":866,"passed_time":0.5994254141,"remaining_time":0.09195337955},
{"learn":[3.238676314],"iteration":867,"passed_time":0.5999175546,"remaining_time":0.09123170185},
{"learn":[3.237848782],"iteration":868,"passed_time":0.600504395,"remaining_time":0.09052482824},
{"learn":[3.236405498],"iteration":869,"passed_time":0.6010219023,"remaining_time":0.08980787046},
{"learn":[3.233378068],"iteration":870,"passed_time":0.6015666423,"remaining_time":0.08909540396},
{"learn":[3.233169169],"iteration":871,"passed_time":0.6020832317,"remaining_time":0.08837918998},
{"learn":[3.232434885],"iteration":872,"passed_time":0.6026128283,"remaining_time":0.08766532553},
{"learn":[3.229978115],"iteration":873,"passed_time":0.6031310949,"remaining_time":0.08695024938},
{"learn":[3.229648848],"iteration":874,"passed_time":0.6036373014,"remaining_time":0.0862339002},
{"learn":[3.227208761],"iteration":875,"passed_time":0.6041306805,"remaining_time":0.08551621505},
{"learn":[3.226258869],"iteration":876,"passed_time":0.6046334045,"remaining_time":0.08480035206},
{"learn":[3.225331995],"iteration":877,"passed_time":0.6053003806,"remaining_time":0.08410779777},
{"learn":[3.221968268],"iteration":878,"passed_time":0.6059287637,"remaining_time":0.08340998909},
{"learn":[3.221166317],"iteration":879,"passed_time":0.6065565444,"remaining_time":0.08271225606},
{"learn":[3.220047503],"iteration":880,"passed_time":0.60728559,"remaining_time":0.08202836005},
{"learn":[3.21982781],"iteration":881,"passed_time":0.6078096935,"remaining_time":0.08131694312},
{"learn":[3.216693405],"iteration":882,"passed_time":0.6084301495,"remaining_time":0.08061871743},
{"learn":[3.214798761],"iteration":883,"passed_time":0.6091021733,"remaining_time":0.07992743451},
{"learn":[3.214395085],"iteration":884,"passed_time":0.6096907441,"remaining_time":0.07922535093},
{"learn":[3.213470696],"iteration":885,"passed_time":0.610272811,"remaining_time":0.07852268675},
{"learn":[3.211595017],"iteration":886,"passed_time":0.6107773328,"remaining_time":0.07781041557},
{"learn":[3.210965255],"iteration":887,"passed_time":0.6113023044,"remaining_time":0.07710119154},
{"learn":[3.209413583],"iteration":888,"passed_time":0.6118277785,"remaining_time":0.07639244479},
{"learn":[3.208331683],"iteration":889,"passed_time":0.612330776,"remaining_time":0.07568133186},
{"learn":[3.207110711],"iteration":890,"passed_time":0.612897256,"remaining_time":0.07497845219},
{"learn":[3.204519413],"iteration":891,"passed_time":0.6134189314,"remaining_time":0.07427045358},
{"learn":[3.201421296],"iteration":892,"passed_time":0.6139749808,"remaining_time":0.07356699098},
{"learn":[3.200691259],"iteration":893,"passed_time":0.6144619657,"remaining_time":0.07285566932},
{"learn":[3.200485067],"iteration":894,"passed_time":0.6149572192,"remaining_time":0.07214581902},
{"learn":[3.197467568],"iteration":895,"passed_time":0.6155119977,"remaining_time":0.07144335687},
{"learn":[3.195838544],"iteration":896,"passed_time":0.6160741596,"remaining_time":0.07074207183},
{"learn":[3.195671746],"iteration":897,"passed_time":0.6165886982,"remaining_time":0.07003568733},
{"learn":[3.194213094],"iteration":898,"passed_time":0.6171167187,"remaining_time":0.06933124426},
{"learn":[3.192884691],"iteration":899,"passed_time":0.617651405,"remaining_time":0.06862793389},
{"learn":[3.188364239],"iteration":900,"passed_time":0.6181821103,"remaining_time":0.0679245604},
{"learn":[3.185219478],"iteration":901,"passed_time":0.6187024817,"remaining_time":0.06722044701},
{"learn":[3.184120387],"iteration":902,"passed_time":0.6192866083,"remaining_time":0.06652358915},
{"learn":[3.183725321],"iteration":903,"passed_time":0.6199127058,"remaining_time":0.06583143779},
{"learn":[3.181264554],"iteration":904,"passed_time":0.6204703774,"remaining_time":0.06513224956},
{"learn":[3.180741589],"iteration":905,"passed_time":0.6209626838,"remaining_time":0.06442659192},
{"learn":[3.179782639],"iteration":906,"passed_time":0.6214424237,"remaining_time":0.06372011621},
{"learn":[3.176377564],"iteration":907,"passed_time":0.6219743701,"remaining_time":0.06301942957},
{"learn":[3.174078182],"iteration":908,"passed_time":0.6225088097,"remaining_time":0.06231936379},
{"learn":[3.171242379],"iteration":909,"passed_time":0.623121549,"remaining_time":0.06162740594},
{"learn":[3.170421012],"iteration":910,"passed_time":0.6237556848,"remaining_time":0.06093771234},
{"learn":[3.170087224],"iteration":911,"passed_time":0.6242561705,"remaining_time":0.06023524452},
{"learn":[3.167303059],"iteration":912,"passed_time":0.624771037,"remaining_time":0.0595345895},
{"learn":[3.16705966],"iteration":913,"passed_time":0.6252301664,"remaining_time":0.05882909662},
{"learn":[3.165667683],"iteration":914,"passed_time":0.6256675432,"remaining_time":0.0581221215},
{"learn":[3.164689733],"iteration":915,"passed_time":0.6261449964,"remaining_time":0.05741941015},
{"learn":[3.163311455],"iteration":916,"passed_time":0.6266406164,"remaining_time":0.05671883442},
{"learn":[3.159425016],"iteration":917,"passed_time":0.6270958273,"remaining_time":0.05601509569},
{"learn":[3.159327058],"iteration":918,"passed_time":0.6275437676,"remaining_time":0.05531125699},
{"learn":[3.15819426],"iteration":919,"passed_time":0.6280029856,"remaining_time":0.05460895527},
{"learn":[3.157086603],"iteration":920,"passed_time":0.6284836905,"remaining_time":0.05390902449},
{"learn":[3.153354154],"iteration":921,"passed_time":0.6289653071,"remaining_time":0.05320964637},
{"learn":[3.153261317],"iteration":922,"passed_time":0.6294121996,"remaining_time":0.0525078433},
{"learn":[3.153168454],"iteration":923,"passed_time":0.6298820926,"remaining_time":0.05180848381},
{"learn":[3.152080399],"iteration":924,"passed_time":0.6304256055,"remaining_time":0.05111558964},
{"learn":[3.151635144],"iteration":925,"passed_time":0.6309503092,"remaining_time":0.05042151499},
{"learn":[3.147762655],"iteration":926,"passed_time":0.6314374306,"remaining_time":0.04972484621},
{"learn":[3.147172317],"iteration":927,"passed_time":0.6319336548,"remaining_time":0.04902933529},
{"learn":[3.146254125],"iteration":928,"passed_time":0.6324060957,"remaining_time":0.04833243573},
{"learn":[3.144869828],"iteration":929,"passed_time":0.6328838094,"remaining_time":0.04763641576},
{"learn":[3.143466218],"iteration":930,"passed_time":0.6333299213,"remaining_time":0.04693852263},
{"learn":[3.141919643],"iteration":931,"passed_time":0.6338029478,"remaining_time":0.04624313353},
{"learn":[3.141054135],"iteration":932,"passed_time":0.6342959157,"remaining_time":0.04554965311},
{"learn":[3.139390417],"iteration":933,"passed_time":0.6347875644,"remaining_time":0.04485650883},
{"learn":[3.139025283],"iteration":934,"passed_time":0.6352296804,"remaining_time":0.04416035212},
{"learn":[3.137824183],"iteration":935,"passed_time":0.635707188,"remaining_time":0.04346715815},
{"learn":[3.135620453],"iteration":936,"passed_time":0.6362237131,"remaining_time":0.04277704794},
{"learn":[3.13443178],"iteration":937,"passed_time":0.6367168202,"remaining_time":0.04208575997},
{"learn":[3.132765713],"iteration":938,"passed_time":0.6371924548,"remaining_time":0.04139375904},
{"learn":[3.131434124],"iteration":939,"passed_time":0.6376750208,"remaining_time":0.0407026609},
{"learn":[3.128384262],"iteration":940,"passed_time":0.6381999391,"remaining_time":0.04001466143},
{"learn":[3.128120455],"iteration":941,"passed_time":0.6387315012,"remaining_time":0.03932741727},
{"learn":[3.126314615],"iteration":942,"passed_time":0.6392573634,"remaining_time":0.03864015876},
{"learn":[3.125409666],"iteration":943,"passed_time":0.639782291,"remaining_time":0.03795318676},
{"learn":[3.123072589],"iteration":944,"passed_time":0.640396094,"remaining_time":0.03727173034},
{"learn":[3.122921099],"iteration":945,"passed_time":0.6409274392,"remaining_time":0.03658571006},
{"learn":[3.122182662],"iteration":946,"passed_time":0.6414443214,"remaining_time":0.03589920701},
{"learn":[3.120040951],"iteration":947,"passed_time":0.6420334332,"remaining_time":0.03521702376},
{"learn":[3.118767799],"iteration":948,"passed_time":0.6426600926,"remaining_time":0.0345370545},
{"learn":[3.118203218],"iteration":949,"passed_time":0.6431938502,"remaining_time":0.0338523079},
{"learn":[3.116343362],"iteration":950,"passed_time":0.6437078442,"remaining_time":0.03316686053},
{"learn":[3.11480829],"iteration":951,"passed_time":0.6443052201,"remaining_time":0.03248597748},
{"learn":[3.112607903],"iteration":952,"passed_time":0.6448618041,"remaining_time":0.03180325791},
{"learn":[3.111661241],"iteration":953,"passed_time":0.645402024,"remaining_time":0.03112001373},
{"learn":[3.110249676],"iteration":954,"passed_time":0.6459721482,"remaining_time":0.03043847819},
{"learn":[3.107333579],"iteration":955,"passed_time":0.646495025,"remaining_time":0.02975500115},
{"learn":[3.107149851],"iteration":956,"passed_time":0.6469880786,"remaining_time":0.02907051973},
{"learn":[3.106867336],"iteration":957,"passed_time":0.6474663503,"remaining_time":0.02838578989},
{"learn":[3.10364681],"iteration":958,"passed_time":0.6480620936,"remaining_time":0.02770651287},
{"learn":[3.102703811],"iteration":959,"passed_time":0.6486277823,"remaining_time":0.02702615759},
{"learn":[3.101469264],"iteration":960,"passed_time":0.6491855673,"remaining_time":0.02634572021},
{"learn":[3.09863569],"iteration":961,"passed_time":0.6496722073,"remaining_time":0.02566272752},
{"learn":[3.09645939],"iteration":962,"passed_time":0.6501603646,"remaining_time":0.02498020092},
{"learn":[3.096240186],"iteration":963,"passed_time":0.6507738967,"remaining_time":0.02430275963},
{"learn":[3.094838828],"iteration":964,"passed_time":0.6513118314,"remaining_time":0.02362270891},
{"learn":[3.094176802],"iteration":965,"passed_time":0.6518425534,"remaining_time":0.02294269857},
{"learn":[3.093182279],"iteration":966,"passed_time":0.652385762,"remaining_time":0.02226342311},
{"learn":[3.090150687],"iteration":967,"passed_time":0.652944015,"remaining_time":0.02158492612},
{"learn":[3.088612829],"iteration":968,"passed_time":0.6534846873,"remaining_time":0.02090611487},
{"learn":[3.087153684],"iteration":969,"passed_time":0.6540043432,"remaining_time":0.02022693845},
{"learn":[3.085866843],"iteration":970,"passed_time":0.6545814127,"remaining_time":0.01954980532},
{"learn":[3.082669094],"iteration":971,"passed_time":0.6551015698,"remaining_time":0.01887123864},
{"learn":[3.081047548],"iteration":972,"passed_time":0.655656679,"remaining_time":0.01819396745},
{"learn":[3.079684322],"iteration":973,"passed_time":0.6562186924,"remaining_time":0.01751713142},
{"learn":[3.07613431],"iteration":974,"passed_time":0.6568046361,"remaining_time":0.01684114452},
{"learn":[3.074005935],"iteration":975,"passed_time":0.6573599671,"remaining_time":0.01616458935},
{"learn":[3.072988853],"iteration":976,"passed_time":0.6578864662,"remaining_time":0.01548760361},
{"learn":[3.072344268],"iteration":977,"passed_time":0.6584043278,"remaining_time":0.0148107313},
{"learn":[3.070654438],"iteration":978,"passed_time":0.6589052845,"remaining_time":0.01413382122},
{"learn":[3.069724506],"iteration":979,"passed_time":0.6594103551,"remaining_time":0.01345735419},
{"learn":[3.067763166],"iteration":980,"passed_time":0.6599423711,"remaining_time":0.01278175846},
{"learn":[3.066737893],"iteration":981,"passed_time":0.6604316766,"remaining_time":0.01210567228},
{"learn":[3.065248174],"iteration":982,"passed_time":0.6609608717,"remaining_time":0.01143065597},
{"learn":[3.063186837],"iteration":983,"passed_time":0.6614776323,"remaining_time":0.01075573386},
{"learn":[3.062880371],"iteration":984,"passed_time":0.6620237589,"remaining_time":0.01008158008},
{"learn":[3.061288645],"iteration":985,"passed_time":0.6625385651,"remaining_time":0.009407241289},
{"learn":[3.059970575],"iteration":986,"passed_time":0.6631069035,"remaining_time":0.008733930846},
{"learn":[3.059576341],"iteration":987,"passed_time":0.6637069559,"remaining_time":0.008061218088},
{"learn":[3.058175919],"iteration":988,"passed_time":0.6642273206,"remaining_time":0.007387765953},
{"learn":[3.056830702],"iteration":989,"passed_time":0.6647348007,"remaining_time":0.006714492936},
{"learn":[3.056336579],"iteration":990,"passed_time":0.6652495734,"remaining_time":0.006041620747},
{"learn":[3.055810414],"iteration":991,"passed_time":0.6658190622,"remaining_time":0.005369508566},
{"learn":[3.055476518],"iteration":992,"passed_time":0.6663962908,"remaining_time":0.004697657639},
{"learn":[3.053331734],"iteration":993,"passed_time":0.6670200921,"remaining_time":0.004026278222},
{"learn":[3.050890374],"iteration":994,"passed_time":0.6675986456,"remaining_time":0.003354767063},
{"learn":[3.04972623],"iteration":995,"passed_time":0.6681217327,"remaining_time":0.00268321981},
{"learn":[3.047217327],"iteration":996,"passed_time":0.6686754682,"remaining_time":0.002012062592},
{"learn":[3.047155483],"iteration":997,"passed_time":0.6691979142,"remaining_time":0.001341077984},
{"learn":[3.04430671],"iteration":998,"passed_time":0.6696897816,"remaining_time":0.0006703601418},
{"learn":[3.042664195],"iteration":999,"passed_time":0.6702470878,"remaining_time":0}
]}